Workbook

Sheet Settings
A1: SHOP SETTINGS | D1: DROP-DOWN LISTS (edit/add below the headers)
D2: Product Categories | E2: Units | F2: Payment Methods | G2: Running Cost Categories | H2: Fixed Cost Categories | I2: Partners | J2: Profit Share %
A3: Shop name | B3: My Bike Parts Shop | D3: Engine Parts | E3: Pcs | F3: Cash | G3: Electricity | H3: Decoration | I3: Partner 1 | J3: 33.333333
A4: Address | B4: Chattogram, Bangladesh | D4: Brakes & Clutch | E4: Kg | F4: bKash | G4: Internet | H4: Furniture | I4: Partner 2 | J4: 33.333333
A5: Phone | B5: 01XXXXXXXXX | D5: Electrical | E5: Box | F5: Nagad | G5: Salary | H5: Equipment | I5: Partner 3 | J5: 33.333333
A6: Memo prefix | B6: INV- | D6: Tyres & Wheels | E6: Set | F6: Card | G6: Rent | H6: Repair
A7: Currency symbol | B7: ৳ | D7: Lubricants | E7: Ft | F7: Bank | G7: Transport | H7: Materials
A8: Default low-stock threshold | B8: 5 | D8: Accessories & Safety | E8: Litre | G8: Other | H8: Other
A9: Report year (drives Profit, Reinvestment, Dashboard) | B9: 2026 | E9: Pair
A10: Opening cash in hand (start of report year) | B10: 0
A11: First year for yearly table | B11: 2026
A12: Max discount % (warn above) | B12: 10
A13: Max buy-price change % (warn above) | B13: 20
A14: HOW TO USE THIS WORKBOOK
A15: Blue header + blue text = you (or the app) type/write here.
A16: Grey header + grey cells = formulas. Never type in them.
A17: Row 2 of Products, Purchases, Sales_Memo, Sales_Items, Due_Payments, Running_Costs, Fixed_Costs and Owner_Capital holds an EXAMPLE row. Delete it before real use.
A18: Stock is never typed: Current = Opening + Purchased - Sold.
A19: Sales_Items 'Buy Price at Sale' is a snapshot written by the app at the time of sale, so old profit stays correct if prices change.
A20: Amount in Words (Sales_Memo) is generated by the app (English, lakh/crore). It is typed in the example only.
A21: Dashboard cost-category tables show the first 6 categories in each Settings list.

Sheet Products
A1: Code | B1: Name | C1: Category | D1: Unit | E1: Buy Price | F1: Sell Price | G1: Min Stock Alert | H1: Supplier | I1: Opening Stock | J1: Active (Y/N) | K1: Margin % | L1: Brand
A2: BP001 | B2: Brake Pad Set - Front | C2: Brakes & Clutch | D2: Set | E2: 320 | F2: 480 | G2: 8 | H2: Chattogram Parts Hub | I2: 40 | J2: Y | L2: TVS
A3: BP002 | B3: Clutch Cable | C3: Brakes & Clutch | D3: Pcs | E3: 110 | F3: 190 | G3: 10 | H3: Rahim Auto Traders | I3: 60 | J3: Y | L3: Bajaj
A4: BP003 | B4: Spark Plug CPR8EA-9 | C4: Engine Parts | D4: Pcs | E4: 175 | F4: 260 | G4: 15 | H4: Dhaka Moto Supply | I4: 100 | J4: Y | L4: NGK
A5: BP004 | B5: Air Filter 150cc | C5: Engine Parts | D5: Pcs | E5: 210 | F5: 340 | G5: 10 | H5: Chattogram Parts Hub | I5: 45 | J5: Y | L5: Honda
A6: BP005 | B6: Chain & Sprocket Kit | C6: Engine Parts | D6: Set | E6: 1750 | F6: 2350 | G6: 4 | H6: Rahim Auto Traders | I6: 18 | J6: Y | K6: =IF(OR(A6="",F6=0),"",(F6-E6)/F6) -> 0.25531915 | L6: Yamaha
A7: BP006 | B7: Engine Oil 10W-30 (1L) | C7: Lubricants | D7: Litre | E7: 620 | F7: 780 | G7: 20 | H7: Dhaka Moto Supply | I7: 90 | J7: Y | K7: =IF(OR(A7="",F7=0),"",(F7-E7)/F7) -> 0.20512821 | L7: Castrol
A8: BP007 | B8: Engine Oil 20W-50 (1L) | C8: Lubricants | D8: Litre | E8: 780 | F8: 990 | G8: 15 | H8: Chattogram Parts Hub | I8: 50 | J8: Y | K8: =IF(OR(A8="",F8=0),"",(F8-E8)/F8) -> 0.21212121 | L8: Motul
A9: BP008 | B9: Headlight Bulb H4 | C9: Electrical | D9: Pcs | E9: 140 | F9: 240 | G9: 12 | H9: Rahim Auto Traders | I9: 70 | J9: Y | K9: =IF(OR(A9="",F9=0),"",(F9-E9)/F9) -> 0.41666667 | L9: Bosch
A10: BP009 | B10: Battery 12V 5Ah | C10: Electrical | D10: Pcs | E10: 2350 | F10: 2950 | G10: 3 | H10: Dhaka Moto Supply | I10: 8 | J10: Y | K10: =IF(OR(A10="",F10=0),"",(F10-E10)/F10) -> 0.20338983 | L10: Exide
A11: BP010 | B11: Tyre 90/90-17 Rear | C11: Tyres & Wheels | D11: Pcs | E11: 2750 | F11: 3350 | G11: 4 | H11: Chattogram Parts Hub | I11: 14 | J11: Y | K11: =IF(OR(A11="",F11=0),"",(F11-E11)/F11) -> 0.17910448 | L11: MRF
A12: BP011 | B12: Tyre 80/100-18 Front | C12: Tyres & Wheels | D12: Pcs | E12: 2300 | F12: 2850 | G12: 4 | H12: Rahim Auto Traders | I12: 10 | J12: Y | K12: =IF(OR(A12="",F12=0),"",(F12-E12)/F12) -> 0.19298246 | L12: CEAT
A13: BP012 | B13: Side Mirror (Pair) | C13: Accessories & Safety | D13: Pair | E13: 380 | F13: 620 | G13: 6 | H13: Dhaka Moto Supply | I13: 25 | J13: Y | K13: =IF(OR(A13="",F13=0),"",(F13-E13)/F13) -> 0.38709677 | L13: Honda
A14: BP013 | B14: Helmet Full Face | C14: Accessories & Safety | D14: Pcs | E14: 1250 | F14: 1750 | G14: 5 | H14: Chattogram Parts Hub | I14: 12 | J14: Y | K14: =IF(OR(A14="",F14=0),"",(F14-E14)/F14) -> 0.28571429 | L14: Steelbird
A15: BP014 | B15: Chain Lube Spray | C15: Lubricants | D15: Pcs | E15: 170 | F15: 270 | G15: 10 | H15: Rahim Auto Traders | I15: 35 | J15: Y | K15: =IF(OR(A15="",F15=0),"",(F15-E15)/F15) -> 0.37037037 | L15: Motul
A16: BP015 | B16: Handle Grip Set | C16: Accessories & Safety | D16: Set | E16: 160 | F16: 280 | G16: 8 | H16: Dhaka Moto Supply | I16: 30 | J16: Y | K16: =IF(OR(A16="",F16=0),"",(F16-E16)/F16) -> 0.42857143 | L16: Vega
K17: =IF(OR(A17="",F17=0),"",(F17-E17)/F17)
K18: =IF(OR(A18="",F18=0),"",(F18-E18)/F18)
K19: =IF(OR(A19="",F19=0),"",(F19-E19)/F19)
K20: =IF(OR(A20="",F20=0),"",(F20-E20)/F20)
K21: =IF(OR(A21="",F21=0),"",(F21-E21)/F21)
K22: =IF(OR(A22="",F22=0),"",(F22-E22)/F22)
K23: =IF(OR(A23="",F23=0),"",(F23-E23)/F23)
K24: =IF(OR(A24="",F24=0),"",(F24-E24)/F24)
K25: =IF(OR(A25="",F25=0),"",(F25-E25)/F25)
K26: =IF(OR(A26="",F26=0),"",(F26-E26)/F26)
K27: =IF(OR(A27="",F27=0),"",(F27-E27)/F27)
K28: =IF(OR(A28="",F28=0),"",(F28-E28)/F28)
... K501: =IF(OR(A501="",F501=0),"",(F501-E501)/F501)

Sheet Purchases
A1: Date | B1: Product Code | C1: Product Name | D1: Qty | E1: Unit Cost | F1: Total | G1: Supplier | H1: Invoice No
A2: 46243 | B2: BP014 | C2: =IF(B2="","",IFERROR(INDEX(Products!$B$2:$B$501,MATCH(B2,Products!$A$2:$A$501,0)),"CODE NOT FOUND")) -> Chain Lube Spray | D2: 24 | E2: 170 | G2: Rahim Auto Traders | H2: PUR-001
A3: 46247 | B3: BP015 | C3: =IF(B3="","",IFERROR(INDEX(Products!$B$2:$B$501,MATCH(B3,Products!$A$2:$A$501,0)),"CODE NOT FOUND")) -> Handle Grip Set | D3: 21 | E3: 160 | G3: Chattogram Parts Hub | H3: PUR-002
A4: 46247 | B4: BP002 | C4: =IF(B4="","",IFERROR(INDEX(Products!$B$2:$B$501,MATCH(B4,Products!$A$2:$A$501,0)),"CODE NOT FOUND")) -> Clutch Cable | D4: 42 | E4: 110 | G4: Chattogram Parts Hub | H4: PUR-003
A5: 46248 | B5: BP007 | C5: =IF(B5="","",IFERROR(INDEX(Products!$B$2:$B$501,MATCH(B5,Products!$A$2:$A$501,0)),"CODE NOT FOUND")) -> Engine Oil 20W-50 (1L) | D5: 35 | E5: 780 | G5: Dhaka Moto Supply | H5: PUR-004
A6: 46248 | B6: BP004 | C6: =IF(B6="","",IFERROR(INDEX(Products!$B$2:$B$501,MATCH(B6,Products!$A$2:$A$501,0)),"CODE NOT FOUND")) -> Air Filter 150cc | D6: 31 | E6: 210 | F6: =IF(OR(D6="",E6=""),"",D6*E6) -> 6510 | G6: Rahim Auto Traders | H6: PUR-005
A7: 46248 | B7: BP014 | C7: =IF(B7="","",IFERROR(INDEX(Products!$B$2:$B$501,MATCH(B7,Products!$A$2:$A$501,0)),"CODE NOT FOUND")) -> Chain Lube Spray | D7: 24 | E7: 170 | F7: =IF(OR(D7="",E7=""),"",D7*E7) -> 4080 | G7: Rahim Auto Traders | H7: PUR-006
A8: 46251 | B8: BP008 | C8: =IF(B8="","",IFERROR(INDEX(Products!$B$2:$B$501,MATCH(B8,Products!$A$2:$A$501,0)),"CODE NOT FOUND")) -> Headlight Bulb H4 | D8: 49 | E8: 140 | F8: =IF(OR(D8="",E8=""),"",D8*E8) -> 6860 | G8: Rahim Auto Traders | H8: PUR-007
A9: 46256 | B9: BP012 | C9: =IF(B9="","",IFERROR(INDEX(Products!$B$2:$B$501,MATCH(B9,Products!$A$2:$A$501,0)),"CODE NOT FOUND")) -> Side Mirror (Pair) | D9: 17 | E9: 380 | F9: =IF(OR(D9="",E9=""),"",D9*E9) -> 6460 | G9: Dhaka Moto Supply | H9: PUR-008
A10: 46256 | B10: BP011 | C10: =IF(B10="","",IFERROR(INDEX(Products!$B$2:$B$501,MATCH(B10,Products!$A$2:$A$501,0)),"CODE NOT FOUND")) -> Tyre 80/100-18 Front | D10: 7 | E10: 2300 | F10: =IF(OR(D10="",E10=""),"",D10*E10) -> 16100 | G10: Rahim Auto Traders | H10: PUR-009
A11: 46256 | B11: BP002 | C11: =IF(B11="","",IFERROR(INDEX(Products!$B$2:$B$501,MATCH(B11,Products!$A$2:$A$501,0)),"CODE NOT FOUND")) -> Clutch Cable | D11: 42 | E11: 110 | F11: =IF(OR(D11="",E11=""),"",D11*E11) -> 4620 | G11: Chattogram Parts Hub | H11: PUR-010
A12: 46257 | B12: BP015 | C12: =IF(B12="","",IFERROR(INDEX(Products!$B$2:$B$501,MATCH(B12,Products!$A$2:$A$501,0)),"CODE NOT FOUND")) -> Handle Grip Set | D12: 21 | E12: 160 | F12: =IF(OR(D12="",E12=""),"",D12*E12) -> 3360 | G12: Chattogram Parts Hub | H12: PUR-011
A13: 46260 | B13: BP001 | C13: =IF(B13="","",IFERROR(INDEX(Products!$B$2:$B$501,MATCH(B13,Products!$A$2:$A$501,0)),"CODE NOT FOUND")) -> Brake Pad Set - Front | D13: 28 | E13: 320 | F13: =IF(OR(D13="",E13=""),"",D13*E13) -> 8960 | G13: Rahim Auto Traders | H13: PUR-012
A14: 46260 | B14: BP014 | C14: =IF(B14="","",IFERROR(INDEX(Products!$B$2:$B$501,MATCH(B14,Products!$A$2:$A$501,0)),"CODE NOT FOUND")) -> Chain Lube Spray | D14: 24 | E14: 170 | F14: =IF(OR(D14="",E14=""),"",D14*E14) -> 4080 | G14: Rahim Auto Traders | H14: PUR-013
A15: 46266 | B15: BP003 | C15: =IF(B15="","",IFERROR(INDEX(Products!$B$2:$B$501,MATCH(B15,Products!$A$2:$A$501,0)),"CODE NOT FOUND")) -> Spark Plug CPR8EA-9 | D15: 70 | E15: 175 | F15: =IF(OR(D15="",E15=""),"",D15*E15) -> 12250 | G15: Chattogram Parts Hub | H15: PUR-014
A16: 46267 | B16: BP015 | C16: =IF(B16="","",IFERROR(INDEX(Products!$B$2:$B$501,MATCH(B16,Products!$A$2:$A$501,0)),"CODE NOT FOUND")) -> Handle Grip Set | D16: 21 | E16: 160 | F16: =IF(OR(D16="",E16=""),"",D16*E16) -> 3360 | G16: Chattogram Parts Hub | H16: PUR-015
A17: 46267 | B17: BP004 | C17: =IF(B17="","",IFERROR(INDEX(Products!$B$2:$B$501,MATCH(B17,Products!$A$2:$A$501,0)),"CODE NOT FOUND")) -> Air Filter 150cc | D17: 31 | E17: 210 | F17: =IF(OR(D17="",E17=""),"",D17*E17) -> 6510 | G17: Rahim Auto Traders | H17: PUR-016
... A56: 46317 | B56: BP014 | C56: =IF(B56="","",IFERROR(INDEX(Products!$B$2:$B$501,MATCH(B56,Products!$A$2:$A$501,0)),"CODE NOT FOUND")) -> Chain Lube Spray | D56: 24 | E56: 170 | F56: =IF(OR(D56="",E56=""),"",D56*E56) -> 4080 | G56: Rahim Auto Traders | H56: PUR-055
C57: =IF(B57="","",IFERROR(INDEX(Products!$B$2:$B$501,MATCH(B57,Products!$A$2:$A$501,0)),"CODE NOT FOUND")) | F57: =IF(OR(D57="",E57=""),"",D57*E57)
C58: =IF(B58="","",IFERROR(INDEX(Products!$B$2:$B$501,MATCH(B58,Products!$A$2:$A$501,0)),"CODE NOT FOUND")) | F58: =IF(OR(D58="",E58=""),"",D58*E58)
C59: =IF(B59="","",IFERROR(INDEX(Products!$B$2:$B$501,MATCH(B59,Products!$A$2:$A$501,0)),"CODE NOT FOUND")) | F59: =IF(OR(D59="",E59=""),"",D59*E59)
C60: =IF(B60="","",IFERROR(INDEX(Products!$B$2:$B$501,MATCH(B60,Products!$A$2:$A$501,0)),"CODE NOT FOUND")) | F60: =IF(OR(D60="",E60=""),"",D60*E60)
C61: =IF(B61="","",IFERROR(INDEX(Products!$B$2:$B$501,MATCH(B61,Products!$A$2:$A$501,0)),"CODE NOT FOUND")) | F61: =IF(OR(D61="",E61=""),"",D61*E61)
C62: =IF(B62="","",IFERROR(INDEX(Products!$B$2:$B$501,MATCH(B62,Products!$A$2:$A$501,0)),"CODE NOT FOUND")) | F62: =IF(OR(D62="",E62=""),"",D62*E62)
C63: =IF(B63="","",IFERROR(INDEX(Products!$B$2:$B$501,MATCH(B63,Products!$A$2:$A$501,0)),"CODE NOT FOUND")) | F63: =IF(OR(D63="",E63=""),"",D63*E63)
C64: =IF(B64="","",IFERROR(INDEX(Products!$B$2:$B$501,MATCH(B64,Products!$A$2:$A$501,0)),"CODE NOT FOUND")) | F64: =IF(OR(D64="",E64=""),"",D64*E64)
C65: =IF(B65="","",IFERROR(INDEX(Products!$B$2:$B$501,MATCH(B65,Products!$A$2:$A$501,0)),"CODE NOT FOUND")) | F65: =IF(OR(D65="",E65=""),"",D65*E65)
C66: =IF(B66="","",IFERROR(INDEX(Products!$B$2:$B$501,MATCH(B66,Products!$A$2:$A$501,0)),"CODE NOT FOUND")) | F66: =IF(OR(D66="",E66=""),"",D66*E66)
C67: =IF(B67="","",IFERROR(INDEX(Products!$B$2:$B$501,MATCH(B67,Products!$A$2:$A$501,0)),"CODE NOT FOUND")) | F67: =IF(OR(D67="",E67=""),"",D67*E67)
C68: =IF(B68="","",IFERROR(INDEX(Products!$B$2:$B$501,MATCH(B68,Products!$A$2:$A$501,0)),"CODE NOT FOUND")) | F68: =IF(OR(D68="",E68=""),"",D68*E68)
... C2001: =IF(B2001="","",IFERROR(INDEX(Products!$B$2:$B$501,MATCH(B2001,Products!$A$2:$A$501,0)),"CODE NOT FOUND")) | F2001: =IF(OR(D2001="",E2001=""),"",D2001*E2001)

Sheet Sales_Memo
A1: Memo No | B1: Date | C1: Customer Name | D1: Phone | E1: Subtotal | F1: Discount | G1: Grand Total | H1: Paid at Sale | I1: Collected Later | J1: Due | K1: Payment Method | L1: Amount in Words | M1: Note
A2: INV-0001 | B2: 46237 | C2: Monir Auto | D2: 01795154811 | F2: 0 | H2: 940 | K2: bKash | L2: Taka Nine Hundred Forty Only
A3: INV-0002 | B3: 46237 | C3: Shakil Auto | D3: 01794541427 | F3: 0 | H3: 2220 | K3: Cash | L3: Taka Two Thousand Two Hundred Twenty Only
A4: INV-0003 | B4: 46237 | C4: Jahid Auto | D4: 01715621083 | F4: 30 | H4: 990 | K4: Cash | L4: Taka Nine Hundred Ninety Only
A5: INV-0004 | B5: 46237 | C5: Alamgir Auto | D5: 01797767996 | F5: 0 | H5: 990 | K5: Cash | L5: Taka Nine Hundred Ninety Only
A6: INV-0005 | B6: 46237 | C6: Jamal Auto | D6: 01770643907 | E6: =IF(A6="","",SUMIFS(Sales_Items!$H$2:$H$3001,Sales_Items!$A$2:$A$3001,A6)) -> 340 | F6: 10 | G6: =IF(A6="","",E6-N(F6)) -> 330 | H6: 330 | I6: =IF(A6="","",SUMIFS(Due_Payments!$C$2:$C$1001,Due_Payments!$B$2:$B$1001,A6)) -> 0 | J6: =IF(A6="","",G6-N(H6)-I6) -> 0 | K6: Cash | L6: Taka Three Hundred Thirty Only
A7: INV-0006 | B7: 46237 | C7: Karim Auto | D7: 01785131377 | E7: =IF(A7="","",SUMIFS(Sales_Items!$H$2:$H$3001,Sales_Items!$A$2:$A$3001,A7)) -> 680 | F7: 50 | G7: =IF(A7="","",E7-N(F7)) -> 630 | H7: 630 | I7: =IF(A7="","",SUMIFS(Due_Payments!$C$2:$C$1001,Due_Payments!$B$2:$B$1001,A7)) -> 0 | J7: =IF(A7="","",G7-N(H7)-I7) -> 0 | K7: bKash | L7: Taka Six Hundred Thirty Only
A8: INV-0007 | B8: 46237 | C8: Kabir Auto | D8: 01778707214 | E8: =IF(A8="","",SUMIFS(Sales_Items!$H$2:$H$3001,Sales_Items!$A$2:$A$3001,A8)) -> 380 | F8: 0 | G8: =IF(A8="","",E8-N(F8)) -> 380 | H8: 0 | I8: =IF(A8="","",SUMIFS(Due_Payments!$C$2:$C$1001,Due_Payments!$B$2:$B$1001,A8)) -> 190 | J8: =IF(A8="","",G8-N(H8)-I8) -> 190 | K8: bKash | L8: Taka Three Hundred Eighty Only
A9: INV-0008 | B9: 46237 | C9: Rahim Auto | D9: 01770717355 | E9: =IF(A9="","",SUMIFS(Sales_Items!$H$2:$H$3001,Sales_Items!$A$2:$A$3001,A9)) -> 2350 | F9: 0 | G9: =IF(A9="","",E9-N(F9)) -> 2350 | H9: 2350 | I9: =IF(A9="","",SUMIFS(Due_Payments!$C$2:$C$1001,Due_Payments!$B$2:$B$1001,A9)) -> 0 | J9: =IF(A9="","",G9-N(H9)-I9) -> 0 | K9: Cash | L9: Taka Two Thousand Three Hundred Fifty Only
A10: INV-0009 | B10: 46237 | C10: Sajid Auto | D10: 01769940718 | E10: =IF(A10="","",SUMIFS(Sales_Items!$H$2:$H$3001,Sales_Items!$A$2:$A$3001,A10)) -> 870 | F10: 0 | G10: =IF(A10="","",E10-N(F10)) -> 870 | H10: 870 | I10: =IF(A10="","",SUMIFS(Due_Payments!$C$2:$C$1001,Due_Payments!$B$2:$B$1001,A10)) -> 0 | J10: =IF(A10="","",G10-N(H10)-I10) -> 0 | K10: Card | L10: Taka Eight Hundred Seventy Only
A11: INV-0010 | B11: 46237 | C11: Rahim Auto | D11: 01770717355 | E11: =IF(A11="","",SUMIFS(Sales_Items!$H$2:$H$3001,Sales_Items!$A$2:$A$3001,A11)) -> 810 | F11: 0 | G11: =IF(A11="","",E11-N(F11)) -> 810 | H11: 0 | I11: =IF(A11="","",SUMIFS(Due_Payments!$C$2:$C$1001,Due_Payments!$B$2:$B$1001,A11)) -> 400 | J11: =IF(A11="","",G11-N(H11)-I11) -> 410 | K11: Cash | L11: Taka Eight Hundred Ten Only
A12: INV-0011 | B12: 46237 | C12: Jamal Auto | D12: 01770643907 | E12: =IF(A12="","",SUMIFS(Sales_Items!$H$2:$H$3001,Sales_Items!$A$2:$A$3001,A12)) -> 280 | F12: 0 | G12: =IF(A12="","",E12-N(F12)) -> 280 | H12: 280 | I12: =IF(A12="","",SUMIFS(Due_Payments!$C$2:$C$1001,Due_Payments!$B$2:$B$1001,A12)) -> 0 | J12: =IF(A12="","",G12-N(H12)-I12) -> 0 | K12: bKash | L12: Taka Two Hundred Eighty Only
A13: INV-0012 | B13: 46237 | C13: Shakil Auto | D13: 01794541427 | E13: =IF(A13="","",SUMIFS(Sales_Items!$H$2:$H$3001,Sales_Items!$A$2:$A$3001,A13)) -> 340 | F13: 0 | G13: =IF(A13="","",E13-N(F13)) -> 340 | H13: 340 | I13: =IF(A13="","",SUMIFS(Due_Payments!$C$2:$C$1001,Due_Payments!$B$2:$B$1001,A13)) -> 0 | J13: =IF(A13="","",G13-N(H13)-I13) -> 0 | K13: bKash | L13: Taka Three Hundred Forty Only
A14: INV-0013 | B14: 46238 | C14: Monir Auto | D14: 01795154811 | E14: =IF(A14="","",SUMIFS(Sales_Items!$H$2:$H$3001,Sales_Items!$A$2:$A$3001,A14)) -> 680 | F14: 0 | G14: =IF(A14="","",E14-N(F14)) -> 680 | H14: 0 | I14: =IF(A14="","",SUMIFS(Due_Payments!$C$2:$C$1001,Due_Payments!$B$2:$B$1001,A14)) -> 680 | J14: =IF(A14="","",G14-N(H14)-I14) -> 0 | K14: Cash | L14: Taka Six Hundred Eighty Only
A15: INV-0014 | B15: 46238 | C15: Nasir Auto | D15: 01778161301 | E15: =IF(A15="","",SUMIFS(Sales_Items!$H$2:$H$3001,Sales_Items!$A$2:$A$3001,A15)) -> 840 | F15: 0 | G15: =IF(A15="","",E15-N(F15)) -> 840 | H15: 840 | I15: =IF(A15="","",SUMIFS(Due_Payments!$C$2:$C$1001,Due_Payments!$B$2:$B$1001,A15)) -> 0 | J15: =IF(A15="","",G15-N(H15)-I15) -> 0 | K15: Cash | L15: Taka Eight Hundred Forty Only
A16: INV-0015 | B16: 46238 | C16: Jahid Auto | D16: 01715621083 | E16: =IF(A16="","",SUMIFS(Sales_Items!$H$2:$H$3001,Sales_Items!$A$2:$A$3001,A16)) -> 1190 | F16: 0 | G16: =IF(A16="","",E16-N(F16)) -> 1190 | H16: 1190 | I16: =IF(A16="","",SUMIFS(Due_Payments!$C$2:$C$1001,Due_Payments!$B$2:$B$1001,A16)) -> 0 | J16: =IF(A16="","",G16-N(H16)-I16) -> 0 | K16: Cash | L16: Taka One Thousand One Hundred Ninety Only
A17: INV-0016 | B17: 46238 | C17: Karim Auto | D17: 01785131377 | E17: =IF(A17="","",SUMIFS(Sales_Items!$H$2:$H$3001,Sales_Items!$A$2:$A$3001,A17)) -> 1520 | F17: 0 | G17: =IF(A17="","",E17-N(F17)) -> 1520 | H17: 1520 | I17: =IF(A17="","",SUMIFS(Due_Payments!$C$2:$C$1001,Due_Payments!$B$2:$B$1001,A17)) -> 0 | J17: =IF(A17="","",G17-N(H17)-I17) -> 0 | K17: Nagad | L17: Taka One Thousand Five Hundred Twenty Only
... A668: INV-0667 | B668: 46317 | C668: Faruk Auto | D668: 01788837457 | E668: =IF(A668="","",SUMIFS(Sales_Items!$H$2:$H$3001,Sales_Items!$A$2:$A$3001,A668)) -> 520 | F668: 0 | G668: =IF(A668="","",E668-N(F668)) -> 520 | H668: 520 | I668: =IF(A668="","",SUMIFS(Due_Payments!$C$2:$C$1001,Due_Payments!$B$2:$B$1001,A668)) -> 0 | J668: =IF(A668="","",G668-N(H668)-I668) -> 0 | K668: Cash | L668: Taka Five Hundred Twenty Only
E669: =IF(A669="","",SUMIFS(Sales_Items!$H$2:$H$3001,Sales_Items!$A$2:$A$3001,A669)) | G669: =IF(A669="","",E669-N(F669)) | I669: =IF(A669="","",SUMIFS(Due_Payments!$C$2:$C$1001,Due_Payments!$B$2:$B$1001,A669)) | J669: =IF(A669="","",G669-N(H669)-I669)
E670: =IF(A670="","",SUMIFS(Sales_Items!$H$2:$H$3001,Sales_Items!$A$2:$A$3001,A670)) | G670: =IF(A670="","",E670-N(F670)) | I670: =IF(A670="","",SUMIFS(Due_Payments!$C$2:$C$1001,Due_Payments!$B$2:$B$1001,A670)) | J670: =IF(A670="","",G670-N(H670)-I670)
E671: =IF(A671="","",SUMIFS(Sales_Items!$H$2:$H$3001,Sales_Items!$A$2:$A$3001,A671)) | G671: =IF(A671="","",E671-N(F671)) | I671: =IF(A671="","",SUMIFS(Due_Payments!$C$2:$C$1001,Due_Payments!$B$2:$B$1001,A671)) | J671: =IF(A671="","",G671-N(H671)-I671)
E672: =IF(A672="","",SUMIFS(Sales_Items!$H$2:$H$3001,Sales_Items!$A$2:$A$3001,A672)) | G672: =IF(A672="","",E672-N(F672)) | I672: =IF(A672="","",SUMIFS(Due_Payments!$C$2:$C$1001,Due_Payments!$B$2:$B$1001,A672)) | J672: =IF(A672="","",G672-N(H672)-I672)
E673: =IF(A673="","",SUMIFS(Sales_Items!$H$2:$H$3001,Sales_Items!$A$2:$A$3001,A673)) | G673: =IF(A673="","",E673-N(F673)) | I673: =IF(A673="","",SUMIFS(Due_Payments!$C$2:$C$1001,Due_Payments!$B$2:$B$1001,A673)) | J673: =IF(A673="","",G673-N(H673)-I673)
E674: =IF(A674="","",SUMIFS(Sales_Items!$H$2:$H$3001,Sales_Items!$A$2:$A$3001,A674)) | G674: =IF(A674="","",E674-N(F674)) | I674: =IF(A674="","",SUMIFS(Due_Payments!$C$2:$C$1001,Due_Payments!$B$2:$B$1001,A674)) | J674: =IF(A674="","",G674-N(H674)-I674)
E675: =IF(A675="","",SUMIFS(Sales_Items!$H$2:$H$3001,Sales_Items!$A$2:$A$3001,A675)) | G675: =IF(A675="","",E675-N(F675)) | I675: =IF(A675="","",SUMIFS(Due_Payments!$C$2:$C$1001,Due_Payments!$B$2:$B$1001,A675)) | J675: =IF(A675="","",G675-N(H675)-I675)
E676: =IF(A676="","",SUMIFS(Sales_Items!$H$2:$H$3001,Sales_Items!$A$2:$A$3001,A676)) | G676: =IF(A676="","",E676-N(F676)) | I676: =IF(A676="","",SUMIFS(Due_Payments!$C$2:$C$1001,Due_Payments!$B$2:$B$1001,A676)) | J676: =IF(A676="","",G676-N(H676)-I676)
E677: =IF(A677="","",SUMIFS(Sales_Items!$H$2:$H$3001,Sales_Items!$A$2:$A$3001,A677)) | G677: =IF(A677="","",E677-N(F677)) | I677: =IF(A677="","",SUMIFS(Due_Payments!$C$2:$C$1001,Due_Payments!$B$2:$B$1001,A677)) | J677: =IF(A677="","",G677-N(H677)-I677)
E678: =IF(A678="","",SUMIFS(Sales_Items!$H$2:$H$3001,Sales_Items!$A$2:$A$3001,A678)) | G678: =IF(A678="","",E678-N(F678)) | I678: =IF(A678="","",SUMIFS(Due_Payments!$C$2:$C$1001,Due_Payments!$B$2:$B$1001,A678)) | J678: =IF(A678="","",G678-N(H678)-I678)
E679: =IF(A679="","",SUMIFS(Sales_Items!$H$2:$H$3001,Sales_Items!$A$2:$A$3001,A679)) | G679: =IF(A679="","",E679-N(F679)) | I679: =IF(A679="","",SUMIFS(Due_Payments!$C$2:$C$1001,Due_Payments!$B$2:$B$1001,A679)) | J679: =IF(A679="","",G679-N(H679)-I679)
E680: =IF(A680="","",SUMIFS(Sales_Items!$H$2:$H$3001,Sales_Items!$A$2:$A$3001,A680)) | G680: =IF(A680="","",E680-N(F680)) | I680: =IF(A680="","",SUMIFS(Due_Payments!$C$2:$C$1001,Due_Payments!$B$2:$B$1001,A680)) | J680: =IF(A680="","",G680-N(H680)-I680)
... E1001: =IF(A1001="","",SUMIFS(Sales_Items!$H$2:$H$3001,Sales_Items!$A$2:$A$3001,A1001)) | G1001: =IF(A1001="","",E1001-N(F1001)) | I1001: =IF(A1001="","",SUMIFS(Due_Payments!$C$2:$C$1001,Due_Payments!$B$2:$B$1001,A1001)) | J1001: =IF(A1001="","",G1001-N(H1001)-I1001)

Sheet Sales_Items
A1: Memo No | B1: Date | C1: Product Code | D1: Product Name | E1: Qty | F1: Unit Price | G1: Buy Price at Sale | H1: Line Total | I1: Line Cost | J1: Line Profit
A2: INV-0001 | B2: =IF(A2="","",IFERROR(INDEX(Sales_Memo!$B$2:$B$1001,MATCH(A2,Sales_Memo!$A$2:$A$1001,0)),"")) -> 46237 | C2: BP002 | D2: =IF(C2="","",IFERROR(INDEX(Products!$B$2:$B$501,MATCH(C2,Products!$A$2:$A$501,0)),"CODE NOT FOUND")) -> Clutch Cable | E2: 1 | F2: 190 | G2: 110 | H2: =IF(OR(E2="",F2=""),"",E2*F2) -> 190 | I2: =IF(OR(E2="",G2=""),"",E2*G2) -> 110 | J2: =IF(H2="","",H2-I2) -> 80
A3: INV-0001 | B3: =IF(A3="","",IFERROR(INDEX(Sales_Memo!$B$2:$B$1001,MATCH(A3,Sales_Memo!$A$2:$A$1001,0)),"")) -> 46237 | C3: BP014 | D3: =IF(C3="","",IFERROR(INDEX(Products!$B$2:$B$501,MATCH(C3,Products!$A$2:$A$501,0)),"CODE NOT FOUND")) -> Chain Lube Spray | E3: 1 | F3: 270 | G3: 170 | H3: =IF(OR(E3="",F3=""),"",E3*F3) -> 270 | I3: =IF(OR(E3="",G3=""),"",E3*G3) -> 170 | J3: =IF(H3="","",H3-I3) -> 100
A4: INV-0001 | B4: =IF(A4="","",IFERROR(INDEX(Sales_Memo!$B$2:$B$1001,MATCH(A4,Sales_Memo!$A$2:$A$1001,0)),"")) -> 46237 | C4: BP001 | D4: =IF(C4="","",IFERROR(INDEX(Products!$B$2:$B$501,MATCH(C4,Products!$A$2:$A$501,0)),"CODE NOT FOUND")) -> Brake Pad Set - Front | E4: 1 | F4: 480 | G4: 320 | H4: =IF(OR(E4="",F4=""),"",E4*F4) -> 480 | I4: =IF(OR(E4="",G4=""),"",E4*G4) -> 320 | J4: =IF(H4="","",H4-I4) -> 160
A5: INV-0002 | B5: =IF(A5="","",IFERROR(INDEX(Sales_Memo!$B$2:$B$1001,MATCH(A5,Sales_Memo!$A$2:$A$1001,0)),"")) -> 46237 | C5: BP008 | D5: =IF(C5="","",IFERROR(INDEX(Products!$B$2:$B$501,MATCH(C5,Products!$A$2:$A$501,0)),"CODE NOT FOUND")) -> Headlight Bulb H4 | E5: 1 | F5: 240 | G5: 140 | H5: =IF(OR(E5="",F5=""),"",E5*F5) -> 240 | I5: =IF(OR(E5="",G5=""),"",E5*G5) -> 140 | J5: =IF(H5="","",H5-I5) -> 100
A6: INV-0002 | B6: =IF(A6="","",IFERROR(INDEX(Sales_Memo!$B$2:$B$1001,MATCH(A6,Sales_Memo!$A$2:$A$1001,0)),"")) -> 46237 | C6: BP007 | D6: =IF(C6="","",IFERROR(INDEX(Products!$B$2:$B$501,MATCH(C6,Products!$A$2:$A$501,0)),"CODE NOT FOUND")) -> Engine Oil 20W-50 (1L) | E6: 2 | F6: 990 | G6: 780 | H6: =IF(OR(E6="",F6=""),"",E6*F6) -> 1980 | I6: =IF(OR(E6="",G6=""),"",E6*G6) -> 1560 | J6: =IF(H6="","",H6-I6) -> 420
A7: INV-0003 | B7: =IF(A7="","",IFERROR(INDEX(Sales_Memo!$B$2:$B$1001,MATCH(A7,Sales_Memo!$A$2:$A$1001,0)),"")) -> 46237 | C7: BP004 | D7: =IF(C7="","",IFERROR(INDEX(Products!$B$2:$B$501,MATCH(C7,Products!$A$2:$A$501,0)),"CODE NOT FOUND")) -> Air Filter 150cc | E7: 3 | F7: 340 | G7: 210 | H7: =IF(OR(E7="",F7=""),"",E7*F7) -> 1020 | I7: =IF(OR(E7="",G7=""),"",E7*G7) -> 630 | J7: =IF(H7="","",H7-I7) -> 390
A8: INV-0004 | B8: =IF(A8="","",IFERROR(INDEX(Sales_Memo!$B$2:$B$1001,MATCH(A8,Sales_Memo!$A$2:$A$1001,0)),"")) -> 46237 | C8: BP007 | D8: =IF(C8="","",IFERROR(INDEX(Products!$B$2:$B$501,MATCH(C8,Products!$A$2:$A$501,0)),"CODE NOT FOUND")) -> Engine Oil 20W-50 (1L) | E8: 1 | F8: 990 | G8: 780 | H8: =IF(OR(E8="",F8=""),"",E8*F8) -> 990 | I8: =IF(OR(E8="",G8=""),"",E8*G8) -> 780 | J8: =IF(H8="","",H8-I8) -> 210
A9: INV-0005 | B9: =IF(A9="","",IFERROR(INDEX(Sales_Memo!$B$2:$B$1001,MATCH(A9,Sales_Memo!$A$2:$A$1001,0)),"")) -> 46237 | C9: BP004 | D9: =IF(C9="","",IFERROR(INDEX(Products!$B$2:$B$501,MATCH(C9,Products!$A$2:$A$501,0)),"CODE NOT FOUND")) -> Air Filter 150cc | E9: 1 | F9: 340 | G9: 210 | H9: =IF(OR(E9="",F9=""),"",E9*F9) -> 340 | I9: =IF(OR(E9="",G9=""),"",E9*G9) -> 210 | J9: =IF(H9="","",H9-I9) -> 130
A10: INV-0006 | B10: =IF(A10="","",IFERROR(INDEX(Sales_Memo!$B$2:$B$1001,MATCH(A10,Sales_Memo!$A$2:$A$1001,0)),"")) -> 46237 | C10: BP004 | D10: =IF(C10="","",IFERROR(INDEX(Products!$B$2:$B$501,MATCH(C10,Products!$A$2:$A$501,0)),"CODE NOT FOUND")) -> Air Filter 150cc | E10: 2 | F10: 340 | G10: 210 | H10: =IF(OR(E10="",F10=""),"",E10*F10) -> 680 | I10: =IF(OR(E10="",G10=""),"",E10*G10) -> 420 | J10: =IF(H10="","",H10-I10) -> 260
A11: INV-0007 | B11: =IF(A11="","",IFERROR(INDEX(Sales_Memo!$B$2:$B$1001,MATCH(A11,Sales_Memo!$A$2:$A$1001,0)),"")) -> 46237 | C11: BP002 | D11: =IF(C11="","",IFERROR(INDEX(Products!$B$2:$B$501,MATCH(C11,Products!$A$2:$A$501,0)),"CODE NOT FOUND")) -> Clutch Cable | E11: 2 | F11: 190 | G11: 110 | H11: =IF(OR(E11="",F11=""),"",E11*F11) -> 380 | I11: =IF(OR(E11="",G11=""),"",E11*G11) -> 220 | J11: =IF(H11="","",H11-I11) -> 160
A12: INV-0008 | B12: =IF(A12="","",IFERROR(INDEX(Sales_Memo!$B$2:$B$1001,MATCH(A12,Sales_Memo!$A$2:$A$1001,0)),"")) -> 46237 | C12: BP005 | D12: =IF(C12="","",IFERROR(INDEX(Products!$B$2:$B$501,MATCH(C12,Products!$A$2:$A$501,0)),"CODE NOT FOUND")) -> Chain & Sprocket Kit | E12: 1 | F12: 2350 | G12: 1750 | H12: =IF(OR(E12="",F12=""),"",E12*F12) -> 2350 | I12: =IF(OR(E12="",G12=""),"",E12*G12) -> 1750 | J12: =IF(H12="","",H12-I12) -> 600
A13: INV-0009 | B13: =IF(A13="","",IFERROR(INDEX(Sales_Memo!$B$2:$B$1001,MATCH(A13,Sales_Memo!$A$2:$A$1001,0)),"")) -> 46237 | C13: BP002 | D13: =IF(C13="","",IFERROR(INDEX(Products!$B$2:$B$501,MATCH(C13,Products!$A$2:$A$501,0)),"CODE NOT FOUND")) -> Clutch Cable | E13: 1 | F13: 190 | G13: 110 | H13: =IF(OR(E13="",F13=""),"",E13*F13) -> 190 | I13: =IF(OR(E13="",G13=""),"",E13*G13) -> 110 | J13: =IF(H13="","",H13-I13) -> 80
... A1062: INV-0667 | B1062: =IF(A1062="","",IFERROR(INDEX(Sales_Memo!$B$2:$B$1001,MATCH(A1062,Sales_Memo!$A$2:$A$1001,0)),"")) -> 46317 | C1062: BP003 | D1062: =IF(C1062="","",IFERROR(INDEX(Products!$B$2:$B$501,MATCH(C1062,Products!$A$2:$A$501,0)),"CODE NOT FOUND")) -> Spark Plug CPR8EA-9 | E1062: 2 | F1062: 260 | G1062: 175 | H1062: =IF(OR(E1062="",F1062=""),"",E1062*F1062) -> 520 | I1062: =IF(OR(E1062="",G1062=""),"",E1062*G1062) -> 350 | J1062: =IF(H1062="","",H1062-I1062) -> 170
B1063: =IF(A1063="","",IFERROR(INDEX(Sales_Memo!$B$2:$B$1001,MATCH(A1063,Sales_Memo!$A$2:$A$1001,0)),"")) | D1063: =IF(C1063="","",IFERROR(INDEX(Products!$B$2:$B$501,MATCH(C1063,Products!$A$2:$A$501,0)),"CODE NOT FOUND")) | H1063: =IF(OR(E1063="",F1063=""),"",E1063*F1063) | I1063: =IF(OR(E1063="",G1063=""),"",E1063*G1063) | J1063: =IF(H1063="","",H1063-I1063)
B1064: =IF(A1064="","",IFERROR(INDEX(Sales_Memo!$B$2:$B$1001,MATCH(A1064,Sales_Memo!$A$2:$A$1001,0)),"")) | D1064: =IF(C1064="","",IFERROR(INDEX(Products!$B$2:$B$501,MATCH(C1064,Products!$A$2:$A$501,0)),"CODE NOT FOUND")) | H1064: =IF(OR(E1064="",F1064=""),"",E1064*F1064) | I1064: =IF(OR(E1064="",G1064=""),"",E1064*G1064) | J1064: =IF(H1064="","",H1064-I1064)
B1065: =IF(A1065="","",IFERROR(INDEX(Sales_Memo!$B$2:$B$1001,MATCH(A1065,Sales_Memo!$A$2:$A$1001,0)),"")) | D1065: =IF(C1065="","",IFERROR(INDEX(Products!$B$2:$B$501,MATCH(C1065,Products!$A$2:$A$501,0)),"CODE NOT FOUND")) | H1065: =IF(OR(E1065="",F1065=""),"",E1065*F1065) | I1065: =IF(OR(E1065="",G1065=""),"",E1065*G1065) | J1065: =IF(H1065="","",H1065-I1065)
B1066: =IF(A1066="","",IFERROR(INDEX(Sales_Memo!$B$2:$B$1001,MATCH(A1066,Sales_Memo!$A$2:$A$1001,0)),"")) | D1066: =IF(C1066="","",IFERROR(INDEX(Products!$B$2:$B$501,MATCH(C1066,Products!$A$2:$A$501,0)),"CODE NOT FOUND")) | H1066: =IF(OR(E1066="",F1066=""),"",E1066*F1066) | I1066: =IF(OR(E1066="",G1066=""),"",E1066*G1066) | J1066: =IF(H1066="","",H1066-I1066)
B1067: =IF(A1067="","",IFERROR(INDEX(Sales_Memo!$B$2:$B$1001,MATCH(A1067,Sales_Memo!$A$2:$A$1001,0)),"")) | D1067: =IF(C1067="","",IFERROR(INDEX(Products!$B$2:$B$501,MATCH(C1067,Products!$A$2:$A$501,0)),"CODE NOT FOUND")) | H1067: =IF(OR(E1067="",F1067=""),"",E1067*F1067) | I1067: =IF(OR(E1067="",G1067=""),"",E1067*G1067) | J1067: =IF(H1067="","",H1067-I1067)
B1068: =IF(A1068="","",IFERROR(INDEX(Sales_Memo!$B$2:$B$1001,MATCH(A1068,Sales_Memo!$A$2:$A$1001,0)),"")) | D1068: =IF(C1068="","",IFERROR(INDEX(Products!$B$2:$B$501,MATCH(C1068,Products!$A$2:$A$501,0)),"CODE NOT FOUND")) | H1068: =IF(OR(E1068="",F1068=""),"",E1068*F1068) | I1068: =IF(OR(E1068="",G1068=""),"",E1068*G1068) | J1068: =IF(H1068="","",H1068-I1068)
B1069: =IF(A1069="","",IFERROR(INDEX(Sales_Memo!$B$2:$B$1001,MATCH(A1069,Sales_Memo!$A$2:$A$1001,0)),"")) | D1069: =IF(C1069="","",IFERROR(INDEX(Products!$B$2:$B$501,MATCH(C1069,Products!$A$2:$A$501,0)),"CODE NOT FOUND")) | H1069: =IF(OR(E1069="",F1069=""),"",E1069*F1069) | I1069: =IF(OR(E1069="",G1069=""),"",E1069*G1069) | J1069: =IF(H1069="","",H1069-I1069)
B1070: =IF(A1070="","",IFERROR(INDEX(Sales_Memo!$B$2:$B$1001,MATCH(A1070,Sales_Memo!$A$2:$A$1001,0)),"")) | D1070: =IF(C1070="","",IFERROR(INDEX(Products!$B$2:$B$501,MATCH(C1070,Products!$A$2:$A$501,0)),"CODE NOT FOUND")) | H1070: =IF(OR(E1070="",F1070=""),"",E1070*F1070) | I1070: =IF(OR(E1070="",G1070=""),"",E1070*G1070) | J1070: =IF(H1070="","",H1070-I1070)
B1071: =IF(A1071="","",IFERROR(INDEX(Sales_Memo!$B$2:$B$1001,MATCH(A1071,Sales_Memo!$A$2:$A$1001,0)),"")) | D1071: =IF(C1071="","",IFERROR(INDEX(Products!$B$2:$B$501,MATCH(C1071,Products!$A$2:$A$501,0)),"CODE NOT FOUND")) | H1071: =IF(OR(E1071="",F1071=""),"",E1071*F1071) | I1071: =IF(OR(E1071="",G1071=""),"",E1071*G1071) | J1071: =IF(H1071="","",H1071-I1071)
B1072: =IF(A1072="","",IFERROR(INDEX(Sales_Memo!$B$2:$B$1001,MATCH(A1072,Sales_Memo!$A$2:$A$1001,0)),"")) | D1072: =IF(C1072="","",IFERROR(INDEX(Products!$B$2:$B$501,MATCH(C1072,Products!$A$2:$A$501,0)),"CODE NOT FOUND")) | H1072: =IF(OR(E1072="",F1072=""),"",E1072*F1072) | I1072: =IF(OR(E1072="",G1072=""),"",E1072*G1072) | J1072: =IF(H1072="","",H1072-I1072)
B1073: =IF(A1073="","",IFERROR(INDEX(Sales_Memo!$B$2:$B$1001,MATCH(A1073,Sales_Memo!$A$2:$A$1001,0)),"")) | D1073: =IF(C1073="","",IFERROR(INDEX(Products!$B$2:$B$501,MATCH(C1073,Products!$A$2:$A$501,0)),"CODE NOT FOUND")) | H1073: =IF(OR(E1073="",F1073=""),"",E1073*F1073) | I1073: =IF(OR(E1073="",G1073=""),"",E1073*G1073) | J1073: =IF(H1073="","",H1073-I1073)
B1074: =IF(A1074="","",IFERROR(INDEX(Sales_Memo!$B$2:$B$1001,MATCH(A1074,Sales_Memo!$A$2:$A$1001,0)),"")) | D1074: =IF(C1074="","",IFERROR(INDEX(Products!$B$2:$B$501,MATCH(C1074,Products!$A$2:$A$501,0)),"CODE NOT FOUND")) | H1074: =IF(OR(E1074="",F1074=""),"",E1074*F1074) | I1074: =IF(OR(E1074="",G1074=""),"",E1074*G1074) | J1074: =IF(H1074="","",H1074-I1074)
... B3001: =IF(A3001="","",IFERROR(INDEX(Sales_Memo!$B$2:$B$1001,MATCH(A3001,Sales_Memo!$A$2:$A$1001,0)),"")) | D3001: =IF(C3001="","",IFERROR(INDEX(Products!$B$2:$B$501,MATCH(C3001,Products!$A$2:$A$501,0)),"CODE NOT FOUND")) | H3001: =IF(OR(E3001="",F3001=""),"",E3001*F3001) | I3001: =IF(OR(E3001="",G3001=""),"",E3001*G3001) | J3001: =IF(H3001="","",H3001-I3001)

Sheet Due_Payments
A1: Date | B1: Memo No | C1: Amount Received | D1: Method | E1: Note
A2: 46243 | B2: INV-0007 | C2: 190 | D2: Cash | E2: Collected
A3: 46249 | B3: INV-0010 | C3: 400 | D3: Cash | E3: Collected
A4: 46247 | B4: INV-0013 | C4: 680 | D4: Cash | E4: Collected
A5: 46243 | B5: INV-0021 | C5: 90 | D5: Cash | E5: Collected
A6: 46246 | B6: INV-0027 | C6: 2720 | D6: Cash | E6: Collected
A7: 46249 | B7: INV-0028 | C7: 220 | D7: Cash | E7: Collected
A8: 46252 | B8: INV-0040 | C8: 680 | D8: Cash | E8: Collected
A9: 46250 | B9: INV-0041 | C9: 220 | D9: Cash | E9: Collected
A10: 46255 | B10: INV-0053 | C10: 510 | D10: Cash | E10: Collected
A11: 46252 | B11: INV-0055 | C11: 60 | D11: Cash | E11: Collected
A12: 46251 | B12: INV-0056 | C12: 370 | D12: Cash | E12: Collected
A13: 46247 | B13: INV-0058 | C13: 60 | D13: Cash | E13: Collected
... A75: 46316 | B75: INV-0604 | C75: 340 | D75: Cash | E75: Collected

Sheet Stock
A1: Code | B1: Name | C1: Category | D1: Opening | E1: Purchased | F1: Sold | G1: Current Stock | H1: Buy Price | I1: Stock Value | J1: Min Alert | K1: Status | L1: Sort Helper | M1: Low-List Helper
A2: =IF(Products!A2="","",Products!A2) -> BP001 | B2: =IF($A2="","",INDEX(Products!$B$2:$B$501,ROW()-1)) -> Brake Pad Set - Front | C2: =IF($A2="","",INDEX(Products!$C$2:$C$501,ROW()-1)) -> Brakes & Clutch | D2: =IF(A2="","",N(Products!I2)) -> 40 | E2: =IF(A2="","",SUMIFS(Purchases!$D$2:$D$2001,Purchases!$B$2:$B$2001,A2)) -> 112 | F2: =IF(A2="","",SUMIFS(Sales_Items!$E$2:$E$3001,Sales_Items!$C$2:$C$3001,A2)) -> 112 | G2: =IF(A2="","",D2+E2-F2) -> 40 | H2: =IF(A2="","",N(Products!E2)) -> 320 | I2: =IF(A2="","",G2*H2) -> 12800 | J2: =IF(A2="","",IF(Products!G2="",Settings!$B$8,Products!G2)) -> 8 | K2: =IF(A2="","",IF(G2<=0,"OUT",IF(G2<=J2,"LOW","OK"))) -> OK | L2: =IF(A2="","",F2+ROW()/1000000) -> 112 | M2: =IF(OR(K2="LOW",K2="OUT"),COUNTIF($K$2:K2,"LOW")+COUNTIF($K$2:K2,"OUT"),"")
A3: =IF(Products!A3="","",Products!A3) -> BP002 | B3: =IF($A3="","",INDEX(Products!$B$2:$B$501,ROW()-1)) -> Clutch Cable | C3: =IF($A3="","",INDEX(Products!$C$2:$C$501,ROW()-1)) -> Brakes & Clutch | D3: =IF(A3="","",N(Products!I3)) -> 60 | E3: =IF(A3="","",SUMIFS(Purchases!$D$2:$D$2001,Purchases!$B$2:$B$2001,A3)) -> 294 | F3: =IF(A3="","",SUMIFS(Sales_Items!$E$2:$E$3001,Sales_Items!$C$2:$C$3001,A3)) -> 347 | G3: =IF(A3="","",D3+E3-F3) -> 7 | H3: =IF(A3="","",N(Products!E3)) -> 110 | I3: =IF(A3="","",G3*H3) -> 770 | J3: =IF(A3="","",IF(Products!G3="",Settings!$B$8,Products!G3)) -> 10 | K3: =IF(A3="","",IF(G3<=0,"OUT",IF(G3<=J3,"LOW","OK"))) -> LOW | L3: =IF(A3="","",F3+ROW()/1000000) -> 347 | M3: =IF(OR(K3="LOW",K3="OUT"),COUNTIF($K$2:K3,"LOW")+COUNTIF($K$2:K3,"OUT"),"") -> 1
A4: =IF(Products!A4="","",Products!A4) -> BP003 | B4: =IF($A4="","",INDEX(Products!$B$2:$B$501,ROW()-1)) -> Spark Plug CPR8EA-9 | C4: =IF($A4="","",INDEX(Products!$C$2:$C$501,ROW()-1)) -> Engine Parts | D4: =IF(A4="","",N(Products!I4)) -> 100 | E4: =IF(A4="","",SUMIFS(Purchases!$D$2:$D$2001,Purchases!$B$2:$B$2001,A4)) -> 210 | F4: =IF(A4="","",SUMIFS(Sales_Items!$E$2:$E$3001,Sales_Items!$C$2:$C$3001,A4)) -> 222 | G4: =IF(A4="","",D4+E4-F4) -> 88 | H4: =IF(A4="","",N(Products!E4)) -> 175 | I4: =IF(A4="","",G4*H4) -> 15400 | J4: =IF(A4="","",IF(Products!G4="",Settings!$B$8,Products!G4)) -> 15 | K4: =IF(A4="","",IF(G4<=0,"OUT",IF(G4<=J4,"LOW","OK"))) -> OK | L4: =IF(A4="","",F4+ROW()/1000000) -> 222 | M4: =IF(OR(K4="LOW",K4="OUT"),COUNTIF($K$2:K4,"LOW")+COUNTIF($K$2:K4,"OUT"),"")
A5: =IF(Products!A5="","",Products!A5) -> BP004 | B5: =IF($A5="","",INDEX(Products!$B$2:$B$501,ROW()-1)) -> Air Filter 150cc | C5: =IF($A5="","",INDEX(Products!$C$2:$C$501,ROW()-1)) -> Engine Parts | D5: =IF(A5="","",N(Products!I5)) -> 45 | E5: =IF(A5="","",SUMIFS(Purchases!$D$2:$D$2001,Purchases!$B$2:$B$2001,A5)) -> 155 | F5: =IF(A5="","",SUMIFS(Sales_Items!$E$2:$E$3001,Sales_Items!$C$2:$C$3001,A5)) -> 174 | G5: =IF(A5="","",D5+E5-F5) -> 26 | H5: =IF(A5="","",N(Products!E5)) -> 210 | I5: =IF(A5="","",G5*H5) -> 5460 | J5: =IF(A5="","",IF(Products!G5="",Settings!$B$8,Products!G5)) -> 10 | K5: =IF(A5="","",IF(G5<=0,"OUT",IF(G5<=J5,"LOW","OK"))) -> OK | L5: =IF(A5="","",F5+ROW()/1000000) -> 174 | M5: =IF(OR(K5="LOW",K5="OUT"),COUNTIF($K$2:K5,"LOW")+COUNTIF($K$2:K5,"OUT"),"")
A6: =IF(Products!A6="","",Products!A6) -> BP005 | B6: =IF($A6="","",INDEX(Products!$B$2:$B$501,ROW()-1)) -> Chain & Sprocket Kit | C6: =IF($A6="","",INDEX(Products!$C$2:$C$501,ROW()-1)) -> Engine Parts | D6: =IF(A6="","",N(Products!I6)) -> 18 | E6: =IF(A6="","",SUMIFS(Purchases!$D$2:$D$2001,Purchases!$B$2:$B$2001,A6)) -> 12 | F6: =IF(A6="","",SUMIFS(Sales_Items!$E$2:$E$3001,Sales_Items!$C$2:$C$3001,A6)) -> 11 | G6: =IF(A6="","",D6+E6-F6) -> 19 | H6: =IF(A6="","",N(Products!E6)) -> 1750 | I6: =IF(A6="","",G6*H6) -> 33250 | J6: =IF(A6="","",IF(Products!G6="",Settings!$B$8,Products!G6)) -> 4 | K6: =IF(A6="","",IF(G6<=0,"OUT",IF(G6<=J6,"LOW","OK"))) -> OK | L6: =IF(A6="","",F6+ROW()/1000000) -> 11.000006 | M6: =IF(OR(K6="LOW",K6="OUT"),COUNTIF($K$2:K6,"LOW")+COUNTIF($K$2:K6,"OUT"),"")
A7: =IF(Products!A7="","",Products!A7) -> BP006 | B7: =IF($A7="","",INDEX(Products!$B$2:$B$501,ROW()-1)) -> Engine Oil 10W-30 (1L) | C7: =IF($A7="","",INDEX(Products!$C$2:$C$501,ROW()-1)) -> Lubricants | D7: =IF(A7="","",N(Products!I7)) -> 90 | E7: =IF(A7="","",SUMIFS(Purchases!$D$2:$D$2001,Purchases!$B$2:$B$2001,A7)) -> 62 | F7: =IF(A7="","",SUMIFS(Sales_Items!$E$2:$E$3001,Sales_Items!$C$2:$C$3001,A7)) -> 101 | G7: =IF(A7="","",D7+E7-F7) -> 51 | H7: =IF(A7="","",N(Products!E7)) -> 620 | I7: =IF(A7="","",G7*H7) -> 31620 | J7: =IF(A7="","",IF(Products!G7="",Settings!$B$8,Products!G7)) -> 20 | K7: =IF(A7="","",IF(G7<=0,"OUT",IF(G7<=J7,"LOW","OK"))) -> OK | L7: =IF(A7="","",F7+ROW()/1000000) -> 101.00001 | M7: =IF(OR(K7="LOW",K7="OUT"),COUNTIF($K$2:K7,"LOW")+COUNTIF($K$2:K7,"OUT"),"")
A8: =IF(Products!A8="","",Products!A8) -> BP007 | B8: =IF($A8="","",INDEX(Products!$B$2:$B$501,ROW()-1)) -> Engine Oil 20W-50 (1L) | C8: =IF($A8="","",INDEX(Products!$C$2:$C$501,ROW()-1)) -> Lubricants | D8: =IF(A8="","",N(Products!I8)) -> 50 | E8: =IF(A8="","",SUMIFS(Purchases!$D$2:$D$2001,Purchases!$B$2:$B$2001,A8)) -> 105 | F8: =IF(A8="","",SUMIFS(Sales_Items!$E$2:$E$3001,Sales_Items!$C$2:$C$3001,A8)) -> 97 | G8: =IF(A8="","",D8+E8-F8) -> 58 | H8: =IF(A8="","",N(Products!E8)) -> 780 | I8: =IF(A8="","",G8*H8) -> 45240 | J8: =IF(A8="","",IF(Products!G8="",Settings!$B$8,Products!G8)) -> 15 | K8: =IF(A8="","",IF(G8<=0,"OUT",IF(G8<=J8,"LOW","OK"))) -> OK | L8: =IF(A8="","",F8+ROW()/1000000) -> 97.000008 | M8: =IF(OR(K8="LOW",K8="OUT"),COUNTIF($K$2:K8,"LOW")+COUNTIF($K$2:K8,"OUT"),"")
A9: =IF(Products!A9="","",Products!A9) -> BP008 | B9: =IF($A9="","",INDEX(Products!$B$2:$B$501,ROW()-1)) -> Headlight Bulb H4 | C9: =IF($A9="","",INDEX(Products!$C$2:$C$501,ROW()-1)) -> Electrical | D9: =IF(A9="","",N(Products!I9)) -> 70 | E9: =IF(A9="","",SUMIFS(Purchases!$D$2:$D$2001,Purchases!$B$2:$B$2001,A9)) -> 245 | F9: =IF(A9="","",SUMIFS(Sales_Items!$E$2:$E$3001,Sales_Items!$C$2:$C$3001,A9)) -> 264 | G9: =IF(A9="","",D9+E9-F9) -> 51 | H9: =IF(A9="","",N(Products!E9)) -> 140 | I9: =IF(A9="","",G9*H9) -> 7140 | J9: =IF(A9="","",IF(Products!G9="",Settings!$B$8,Products!G9)) -> 12 | K9: =IF(A9="","",IF(G9<=0,"OUT",IF(G9<=J9,"LOW","OK"))) -> OK | L9: =IF(A9="","",F9+ROW()/1000000) -> 264.00001 | M9: =IF(OR(K9="LOW",K9="OUT"),COUNTIF($K$2:K9,"LOW")+COUNTIF($K$2:K9,"OUT"),"")
A10: =IF(Products!A10="","",Products!A10) -> BP009 | B10: =IF($A10="","",INDEX(Products!$B$2:$B$501,ROW()-1)) -> Battery 12V 5Ah | C10: =IF($A10="","",INDEX(Products!$C$2:$C$501,ROW()-1)) -> Electrical | D10: =IF(A10="","",N(Products!I10)) -> 8 | E10: =IF(A10="","",SUMIFS(Purchases!$D$2:$D$2001,Purchases!$B$2:$B$2001,A10)) -> 0 | F10: =IF(A10="","",SUMIFS(Sales_Items!$E$2:$E$3001,Sales_Items!$C$2:$C$3001,A10)) -> 8 | G10: =IF(A10="","",D10+E10-F10) -> 0 | H10: =IF(A10="","",N(Products!E10)) -> 2350 | I10: =IF(A10="","",G10*H10) -> 0 | J10: =IF(A10="","",IF(Products!G10="",Settings!$B$8,Products!G10)) -> 3 | K10: =IF(A10="","",IF(G10<=0,"OUT",IF(G10<=J10,"LOW","OK"))) -> OUT | L10: =IF(A10="","",F10+ROW()/1000000) -> 8.00001 | M10: =IF(OR(K10="LOW",K10="OUT"),COUNTIF($K$2:K10,"LOW")+COUNTIF($K$2:K10,"OUT"),"") -> 2
A11: =IF(Products!A11="","",Products!A11) -> BP010 | B11: =IF($A11="","",INDEX(Products!$B$2:$B$501,ROW()-1)) -> Tyre 90/90-17 Rear | C11: =IF($A11="","",INDEX(Products!$C$2:$C$501,ROW()-1)) -> Tyres & Wheels | D11: =IF(A11="","",N(Products!I11)) -> 14 | E11: =IF(A11="","",SUMIFS(Purchases!$D$2:$D$2001,Purchases!$B$2:$B$2001,A11)) -> 9 | F11: =IF(A11="","",SUMIFS(Sales_Items!$E$2:$E$3001,Sales_Items!$C$2:$C$3001,A11)) -> 14 | G11: =IF(A11="","",D11+E11-F11) -> 9 | H11: =IF(A11="","",N(Products!E11)) -> 2750 | I11: =IF(A11="","",G11*H11) -> 24750 | J11: =IF(A11="","",IF(Products!G11="",Settings!$B$8,Products!G11)) -> 4 | K11: =IF(A11="","",IF(G11<=0,"OUT",IF(G11<=J11,"LOW","OK"))) -> OK | L11: =IF(A11="","",F11+ROW()/1000000) -> 14.000011 | M11: =IF(OR(K11="LOW",K11="OUT"),COUNTIF($K$2:K11,"LOW")+COUNTIF($K$2:K11,"OUT"),"")
A12: =IF(Products!A12="","",Products!A12) -> BP011 | B12: =IF($A12="","",INDEX(Products!$B$2:$B$501,ROW()-1)) -> Tyre 80/100-18 Front | C12: =IF($A12="","",INDEX(Products!$C$2:$C$501,ROW()-1)) -> Tyres & Wheels | D12: =IF(A12="","",N(Products!I12)) -> 10 | E12: =IF(A12="","",SUMIFS(Purchases!$D$2:$D$2001,Purchases!$B$2:$B$2001,A12)) -> 14 | F12: =IF(A12="","",SUMIFS(Sales_Items!$E$2:$E$3001,Sales_Items!$C$2:$C$3001,A12)) -> 9 | G12: =IF(A12="","",D12+E12-F12) -> 15 | H12: =IF(A12="","",N(Products!E12)) -> 2300 | I12: =IF(A12="","",G12*H12) -> 34500 | J12: =IF(A12="","",IF(Products!G12="",Settings!$B$8,Products!G12)) -> 4 | K12: =IF(A12="","",IF(G12<=0,"OUT",IF(G12<=J12,"LOW","OK"))) -> OK | L12: =IF(A12="","",F12+ROW()/1000000) -> 9.000012 | M12: =IF(OR(K12="LOW",K12="OUT"),COUNTIF($K$2:K12,"LOW")+COUNTIF($K$2:K12,"OUT"),"")
A13: =IF(Products!A13="","",Products!A13) -> BP012 | B13: =IF($A13="","",INDEX(Products!$B$2:$B$501,ROW()-1)) -> Side Mirror (Pair) | C13: =IF($A13="","",INDEX(Products!$C$2:$C$501,ROW()-1)) -> Accessories & Safety | D13: =IF(A13="","",N(Products!I13)) -> 25 | E13: =IF(A13="","",SUMIFS(Purchases!$D$2:$D$2001,Purchases!$B$2:$B$2001,A13)) -> 68 | F13: =IF(A13="","",SUMIFS(Sales_Items!$E$2:$E$3001,Sales_Items!$C$2:$C$3001,A13)) -> 80 | G13: =IF(A13="","",D13+E13-F13) -> 13 | H13: =IF(A13="","",N(Products!E13)) -> 380 | I13: =IF(A13="","",G13*H13) -> 4940 | J13: =IF(A13="","",IF(Products!G13="",Settings!$B$8,Products!G13)) -> 6 | K13: =IF(A13="","",IF(G13<=0,"OUT",IF(G13<=J13,"LOW","OK"))) -> OK | L13: =IF(A13="","",F13+ROW()/1000000) -> 80.000013 | M13: =IF(OR(K13="LOW",K13="OUT"),COUNTIF($K$2:K13,"LOW")+COUNTIF($K$2:K13,"OUT"),"")
... A501: =IF(Products!A501="","",Products!A501) | B501: =IF($A501="","",INDEX(Products!$B$2:$B$501,ROW()-1)) | C501: =IF($A501="","",INDEX(Products!$C$2:$C$501,ROW()-1)) | D501: =IF(A501="","",N(Products!I501)) | E501: =IF(A501="","",SUMIFS(Purchases!$D$2:$D$2001,Purchases!$B$2:$B$2001,A501)) | F501: =IF(A501="","",SUMIFS(Sales_Items!$E$2:$E$3001,Sales_Items!$C$2:$C$3001,A501)) | G501: =IF(A501="","",D501+E501-F501) | H501: =IF(A501="","",N(Products!E501)) | I501: =IF(A501="","",G501*H501) | J501: =IF(A501="","",IF(Products!G501="",Settings!$B$8,Products!G501)) | K501: =IF(A501="","",IF(G501<=0,"OUT",IF(G501<=J501,"LOW","OK"))) | L501: =IF(A501="","",F501+ROW()/1000000) | M501: =IF(OR(K501="LOW",K501="OUT"),COUNTIF($K$2:K501,"LOW")+COUNTIF($K$2:K501,"OUT"),"")

Sheet Running_Costs
A1: Date | B1: Category | C1: Description | D1: Amount | E1: Paid To
A2: 46239 | B2: Rent | C2: Shop rent | D2: 20000 | E2: Landlord
A3: 46235 | B3: Salary | C3: Staff 1 salary | D3: 12000 | E3: Staff 1
A4: 46235 | B4: Salary | C4: Staff 2 salary | D4: 12000 | E4: Staff 2
A5: 46246 | B5: Electricity | C5: Electricity bill | D5: 3221 | E5: PDB
A6: 46244 | B6: Internet | C6: Net bill | D6: 1000 | E6: ISP
A7: 46249 | B7: Transport | C7: Parts delivery | D7: 1552 | E7: Transport
A8: 46252 | B8: Other | C8: Tea, cleaning, misc | D8: 660
A9: 46270 | B9: Rent | C9: Shop rent | D9: 20000 | E9: Landlord
A10: 46266 | B10: Salary | C10: Staff 1 salary | D10: 12000 | E10: Staff 1
A11: 46266 | B11: Salary | C11: Staff 2 salary | D11: 12000 | E11: Staff 2
A12: 46277 | B12: Electricity | C12: Electricity bill | D12: 2979 | E12: PDB
A13: 46275 | B13: Internet | C13: Net bill | D13: 1000 | E13: ISP
A14: 46280 | B14: Transport | C14: Parts delivery | D14: 2144 | E14: Transport
A15: 46283 | B15: Other | C15: Tea, cleaning, misc | D15: 1468
A16: 46300 | B16: Rent | C16: Shop rent | D16: 20000 | E16: Landlord
A17: 46296 | B17: Salary | C17: Staff 1 salary | D17: 12000 | E17: Staff 1
A18: 46296 | B18: Salary | C18: Staff 2 salary | D18: 12000 | E18: Staff 2
A19: 46307 | B19: Electricity | C19: Electricity bill | D19: 3143 | E19: PDB
A20: 46305 | B20: Internet | C20: Net bill | D20: 1000 | E20: ISP
A21: 46310 | B21: Transport | C21: Parts delivery | D21: 1130 | E21: Transport
A22: 46313 | B22: Other | C22: Tea, cleaning, misc | D22: 907

Sheet Fixed_Costs
A1: Date | B1: Category | C1: Item | D1: Amount | E1: Note
A2: 46223 | B2: Decoration | C2: Shop interior & lighting | D2: 120000 | E2: One-time
A3: 46225 | B3: Furniture | C3: Display racks & counter | D3: 60000 | E3: One-time
A4: 46228 | B4: Equipment | C4: Tools & air compressor | D4: 30000 | E4: One-time
A5: 46231 | B5: Decoration | C5: Signboard & light box | D5: 25000 | E5: One-time
A6: 46236 | B6: Materials | C6: Shelf boxes & packaging | D6: 8000 | E6: One-time

Sheet Owner_Capital
A1: Date | B1: Type | C1: Amount | D1: Note | E1: Partner
A2: 46218 | B2: Capital In | C2: 100000 | D2: Initial capital | E2: Partner 1
A3: 46218 | B3: Capital In | C3: 100000 | D3: Initial capital | E3: Partner 2
A4: 46218 | B4: Capital In | C4: 100000 | D4: Initial capital | E4: Partner 3
A5: 46295 | B5: Owner Drawing | C5: 10000 | D5: Personal use | E5: Partner 1
A6: 46305 | B6: Owner Drawing | C6: 8000 | D6: Personal use | E6: Partner 2

Sheet Profit
A1: PROFIT REPORT
A2: Fixed costs (furniture, decoration...) are one-time investments, so the MAIN profit number is Operating Profit. Fixed costs are shown separately in the last two columns.
A3: MONTHLY (report year from Settings)
A4: Period | B4: Gross Sales | C4: Discounts | D4: Net Sales | E4: Cost of Goods Sold | F4: Gross Profit | G4: Running Costs | H4: OPERATING PROFIT | I4: Fixed Costs | J4: Result after Fixed Costs
A5: =DATE(Settings!$B$9,1,1) -> 46023 | B5: =SUMIFS(Sales_Items!$H$2:$H$3001,Sales_Items!$B$2:$B$3001,">="&$A5,Sales_Items!$B$2:$B$3001,"<"&DATE(YEAR($A5),MONTH($A5)+1,1)) -> 0 | C5: =SUMIFS(Sales_Memo!$F$2:$F$1001,Sales_Memo!$B$2:$B$1001,">="&$A5,Sales_Memo!$B$2:$B$1001,"<"&DATE(YEAR($A5),MONTH($A5)+1,1)) -> 0 | D5: =B5-C5 -> 0 | E5: =SUMIFS(Sales_Items!$I$2:$I$3001,Sales_Items!$B$2:$B$3001,">="&$A5,Sales_Items!$B$2:$B$3001,"<"&DATE(YEAR($A5),MONTH($A5)+1,1)) -> 0 | F5: =D5-E5 -> 0 | G5: =SUMIFS(Running_Costs!$D$2:$D$1001,Running_Costs!$A$2:$A$1001,">="&$A5,Running_Costs!$A$2:$A$1001,"<"&DATE(YEAR($A5),MONTH($A5)+1,1)) -> 0 | H5: =F5-G5 -> 0 | I5: =SUMIFS(Fixed_Costs!$D$2:$D$501,Fixed_Costs!$A$2:$A$501,">="&$A5,Fixed_Costs!$A$2:$A$501,"<"&DATE(YEAR($A5),MONTH($A5)+1,1)) -> 0 | J5: =H5-I5 -> 0
A6: =DATE(Settings!$B$9,2,1) -> 46054 | B6: =SUMIFS(Sales_Items!$H$2:$H$3001,Sales_Items!$B$2:$B$3001,">="&$A6,Sales_Items!$B$2:$B$3001,"<"&DATE(YEAR($A6),MONTH($A6)+1,1)) -> 0 | C6: =SUMIFS(Sales_Memo!$F$2:$F$1001,Sales_Memo!$B$2:$B$1001,">="&$A6,Sales_Memo!$B$2:$B$1001,"<"&DATE(YEAR($A6),MONTH($A6)+1,1)) -> 0 | D6: =B6-C6 -> 0 | E6: =SUMIFS(Sales_Items!$I$2:$I$3001,Sales_Items!$B$2:$B$3001,">="&$A6,Sales_Items!$B$2:$B$3001,"<"&DATE(YEAR($A6),MONTH($A6)+1,1)) -> 0 | F6: =D6-E6 -> 0 | G6: =SUMIFS(Running_Costs!$D$2:$D$1001,Running_Costs!$A$2:$A$1001,">="&$A6,Running_Costs!$A$2:$A$1001,"<"&DATE(YEAR($A6),MONTH($A6)+1,1)) -> 0 | H6: =F6-G6 -> 0 | I6: =SUMIFS(Fixed_Costs!$D$2:$D$501,Fixed_Costs!$A$2:$A$501,">="&$A6,Fixed_Costs!$A$2:$A$501,"<"&DATE(YEAR($A6),MONTH($A6)+1,1)) -> 0 | J6: =H6-I6 -> 0
A7: =DATE(Settings!$B$9,3,1) -> 46082 | B7: =SUMIFS(Sales_Items!$H$2:$H$3001,Sales_Items!$B$2:$B$3001,">="&$A7,Sales_Items!$B$2:$B$3001,"<"&DATE(YEAR($A7),MONTH($A7)+1,1)) -> 0 | C7: =SUMIFS(Sales_Memo!$F$2:$F$1001,Sales_Memo!$B$2:$B$1001,">="&$A7,Sales_Memo!$B$2:$B$1001,"<"&DATE(YEAR($A7),MONTH($A7)+1,1)) -> 0 | D7: =B7-C7 -> 0 | E7: =SUMIFS(Sales_Items!$I$2:$I$3001,Sales_Items!$B$2:$B$3001,">="&$A7,Sales_Items!$B$2:$B$3001,"<"&DATE(YEAR($A7),MONTH($A7)+1,1)) -> 0 | F7: =D7-E7 -> 0 | G7: =SUMIFS(Running_Costs!$D$2:$D$1001,Running_Costs!$A$2:$A$1001,">="&$A7,Running_Costs!$A$2:$A$1001,"<"&DATE(YEAR($A7),MONTH($A7)+1,1)) -> 0 | H7: =F7-G7 -> 0 | I7: =SUMIFS(Fixed_Costs!$D$2:$D$501,Fixed_Costs!$A$2:$A$501,">="&$A7,Fixed_Costs!$A$2:$A$501,"<"&DATE(YEAR($A7),MONTH($A7)+1,1)) -> 0 | J7: =H7-I7 -> 0
A8: =DATE(Settings!$B$9,4,1) -> 46113 | B8: =SUMIFS(Sales_Items!$H$2:$H$3001,Sales_Items!$B$2:$B$3001,">="&$A8,Sales_Items!$B$2:$B$3001,"<"&DATE(YEAR($A8),MONTH($A8)+1,1)) -> 0 | C8: =SUMIFS(Sales_Memo!$F$2:$F$1001,Sales_Memo!$B$2:$B$1001,">="&$A8,Sales_Memo!$B$2:$B$1001,"<"&DATE(YEAR($A8),MONTH($A8)+1,1)) -> 0 | D8: =B8-C8 -> 0 | E8: =SUMIFS(Sales_Items!$I$2:$I$3001,Sales_Items!$B$2:$B$3001,">="&$A8,Sales_Items!$B$2:$B$3001,"<"&DATE(YEAR($A8),MONTH($A8)+1,1)) -> 0 | F8: =D8-E8 -> 0 | G8: =SUMIFS(Running_Costs!$D$2:$D$1001,Running_Costs!$A$2:$A$1001,">="&$A8,Running_Costs!$A$2:$A$1001,"<"&DATE(YEAR($A8),MONTH($A8)+1,1)) -> 0 | H8: =F8-G8 -> 0 | I8: =SUMIFS(Fixed_Costs!$D$2:$D$501,Fixed_Costs!$A$2:$A$501,">="&$A8,Fixed_Costs!$A$2:$A$501,"<"&DATE(YEAR($A8),MONTH($A8)+1,1)) -> 0 | J8: =H8-I8 -> 0
A9: =DATE(Settings!$B$9,5,1) -> 46143 | B9: =SUMIFS(Sales_Items!$H$2:$H$3001,Sales_Items!$B$2:$B$3001,">="&$A9,Sales_Items!$B$2:$B$3001,"<"&DATE(YEAR($A9),MONTH($A9)+1,1)) -> 0 | C9: =SUMIFS(Sales_Memo!$F$2:$F$1001,Sales_Memo!$B$2:$B$1001,">="&$A9,Sales_Memo!$B$2:$B$1001,"<"&DATE(YEAR($A9),MONTH($A9)+1,1)) -> 0 | D9: =B9-C9 -> 0 | E9: =SUMIFS(Sales_Items!$I$2:$I$3001,Sales_Items!$B$2:$B$3001,">="&$A9,Sales_Items!$B$2:$B$3001,"<"&DATE(YEAR($A9),MONTH($A9)+1,1)) -> 0 | F9: =D9-E9 -> 0 | G9: =SUMIFS(Running_Costs!$D$2:$D$1001,Running_Costs!$A$2:$A$1001,">="&$A9,Running_Costs!$A$2:$A$1001,"<"&DATE(YEAR($A9),MONTH($A9)+1,1)) -> 0 | H9: =F9-G9 -> 0 | I9: =SUMIFS(Fixed_Costs!$D$2:$D$501,Fixed_Costs!$A$2:$A$501,">="&$A9,Fixed_Costs!$A$2:$A$501,"<"&DATE(YEAR($A9),MONTH($A9)+1,1)) -> 0 | J9: =H9-I9 -> 0
A10: =DATE(Settings!$B$9,6,1) -> 46174 | B10: =SUMIFS(Sales_Items!$H$2:$H$3001,Sales_Items!$B$2:$B$3001,">="&$A10,Sales_Items!$B$2:$B$3001,"<"&DATE(YEAR($A10),MONTH($A10)+1,1)) -> 0 | C10: =SUMIFS(Sales_Memo!$F$2:$F$1001,Sales_Memo!$B$2:$B$1001,">="&$A10,Sales_Memo!$B$2:$B$1001,"<"&DATE(YEAR($A10),MONTH($A10)+1,1)) -> 0 | D10: =B10-C10 -> 0 | E10: =SUMIFS(Sales_Items!$I$2:$I$3001,Sales_Items!$B$2:$B$3001,">="&$A10,Sales_Items!$B$2:$B$3001,"<"&DATE(YEAR($A10),MONTH($A10)+1,1)) -> 0 | F10: =D10-E10 -> 0 | G10: =SUMIFS(Running_Costs!$D$2:$D$1001,Running_Costs!$A$2:$A$1001,">="&$A10,Running_Costs!$A$2:$A$1001,"<"&DATE(YEAR($A10),MONTH($A10)+1,1)) -> 0 | H10: =F10-G10 -> 0 | I10: =SUMIFS(Fixed_Costs!$D$2:$D$501,Fixed_Costs!$A$2:$A$501,">="&$A10,Fixed_Costs!$A$2:$A$501,"<"&DATE(YEAR($A10),MONTH($A10)+1,1)) -> 0 | J10: =H10-I10 -> 0
A11: =DATE(Settings!$B$9,7,1) -> 46204 | B11: =SUMIFS(Sales_Items!$H$2:$H$3001,Sales_Items!$B$2:$B$3001,">="&$A11,Sales_Items!$B$2:$B$3001,"<"&DATE(YEAR($A11),MONTH($A11)+1,1)) -> 0 | C11: =SUMIFS(Sales_Memo!$F$2:$F$1001,Sales_Memo!$B$2:$B$1001,">="&$A11,Sales_Memo!$B$2:$B$1001,"<"&DATE(YEAR($A11),MONTH($A11)+1,1)) -> 0 | D11: =B11-C11 -> 0 | E11: =SUMIFS(Sales_Items!$I$2:$I$3001,Sales_Items!$B$2:$B$3001,">="&$A11,Sales_Items!$B$2:$B$3001,"<"&DATE(YEAR($A11),MONTH($A11)+1,1)) -> 0 | F11: =D11-E11 -> 0 | G11: =SUMIFS(Running_Costs!$D$2:$D$1001,Running_Costs!$A$2:$A$1001,">="&$A11,Running_Costs!$A$2:$A$1001,"<"&DATE(YEAR($A11),MONTH($A11)+1,1)) -> 0 | H11: =F11-G11 -> 0 | I11: =SUMIFS(Fixed_Costs!$D$2:$D$501,Fixed_Costs!$A$2:$A$501,">="&$A11,Fixed_Costs!$A$2:$A$501,"<"&DATE(YEAR($A11),MONTH($A11)+1,1)) -> 235000 | J11: =H11-I11 -> -235000
A12: =DATE(Settings!$B$9,8,1) -> 46235 | B12: =SUMIFS(Sales_Items!$H$2:$H$3001,Sales_Items!$B$2:$B$3001,">="&$A12,Sales_Items!$B$2:$B$3001,"<"&DATE(YEAR($A12),MONTH($A12)+1,1)) -> 267510 | C12: =SUMIFS(Sales_Memo!$F$2:$F$1001,Sales_Memo!$B$2:$B$1001,">="&$A12,Sales_Memo!$B$2:$B$1001,"<"&DATE(YEAR($A12),MONTH($A12)+1,1)) -> 4390 | D12: =B12-C12 -> 263120 | E12: =SUMIFS(Sales_Items!$I$2:$I$3001,Sales_Items!$B$2:$B$3001,">="&$A12,Sales_Items!$B$2:$B$3001,"<"&DATE(YEAR($A12),MONTH($A12)+1,1)) -> 184760 | F12: =D12-E12 -> 78360 | G12: =SUMIFS(Running_Costs!$D$2:$D$1001,Running_Costs!$A$2:$A$1001,">="&$A12,Running_Costs!$A$2:$A$1001,"<"&DATE(YEAR($A12),MONTH($A12)+1,1)) -> 50433 | H12: =F12-G12 -> 27927 | I12: =SUMIFS(Fixed_Costs!$D$2:$D$501,Fixed_Costs!$A$2:$A$501,">="&$A12,Fixed_Costs!$A$2:$A$501,"<"&DATE(YEAR($A12),MONTH($A12)+1,1)) -> 8000 | J12: =H12-I12 -> 19927
A13: =DATE(Settings!$B$9,9,1) -> 46266 | B13: =SUMIFS(Sales_Items!$H$2:$H$3001,Sales_Items!$B$2:$B$3001,">="&$A13,Sales_Items!$B$2:$B$3001,"<"&DATE(YEAR($A13),MONTH($A13)+1,1)) -> 289970 | C13: =SUMIFS(Sales_Memo!$F$2:$F$1001,Sales_Memo!$B$2:$B$1001,">="&$A13,Sales_Memo!$B$2:$B$1001,"<"&DATE(YEAR($A13),MONTH($A13)+1,1)) -> 5860 | D13: =B13-C13 -> 284110 | E13: =SUMIFS(Sales_Items!$I$2:$I$3001,Sales_Items!$B$2:$B$3001,">="&$A13,Sales_Items!$B$2:$B$3001,"<"&DATE(YEAR($A13),MONTH($A13)+1,1)) -> 197560 | F13: =D13-E13 -> 86550 | G13: =SUMIFS(Running_Costs!$D$2:$D$1001,Running_Costs!$A$2:$A$1001,">="&$A13,Running_Costs!$A$2:$A$1001,"<"&DATE(YEAR($A13),MONTH($A13)+1,1)) -> 51591 | H13: =F13-G13 -> 34959 | I13: =SUMIFS(Fixed_Costs!$D$2:$D$501,Fixed_Costs!$A$2:$A$501,">="&$A13,Fixed_Costs!$A$2:$A$501,"<"&DATE(YEAR($A13),MONTH($A13)+1,1)) -> 0 | J13: =H13-I13 -> 34959
A14: =DATE(Settings!$B$9,10,1) -> 46296 | B14: =SUMIFS(Sales_Items!$H$2:$H$3001,Sales_Items!$B$2:$B$3001,">="&$A14,Sales_Items!$B$2:$B$3001,"<"&DATE(YEAR($A14),MONTH($A14)+1,1)) -> 227530 | C14: =SUMIFS(Sales_Memo!$F$2:$F$1001,Sales_Memo!$B$2:$B$1001,">="&$A14,Sales_Memo!$B$2:$B$1001,"<"&DATE(YEAR($A14),MONTH($A14)+1,1)) -> 5160 | D14: =B14-C14 -> 222370 | E14: =SUMIFS(Sales_Items!$I$2:$I$3001,Sales_Items!$B$2:$B$3001,">="&$A14,Sales_Items!$B$2:$B$3001,"<"&DATE(YEAR($A14),MONTH($A14)+1,1)) -> 155620 | F14: =D14-E14 -> 66750 | G14: =SUMIFS(Running_Costs!$D$2:$D$1001,Running_Costs!$A$2:$A$1001,">="&$A14,Running_Costs!$A$2:$A$1001,"<"&DATE(YEAR($A14),MONTH($A14)+1,1)) -> 50180 | H14: =F14-G14 -> 16570 | I14: =SUMIFS(Fixed_Costs!$D$2:$D$501,Fixed_Costs!$A$2:$A$501,">="&$A14,Fixed_Costs!$A$2:$A$501,"<"&DATE(YEAR($A14),MONTH($A14)+1,1)) -> 0 | J14: =H14-I14 -> 16570
A15: =DATE(Settings!$B$9,11,1) -> 46327 | B15: =SUMIFS(Sales_Items!$H$2:$H$3001,Sales_Items!$B$2:$B$3001,">="&$A15,Sales_Items!$B$2:$B$3001,"<"&DATE(YEAR($A15),MONTH($A15)+1,1)) -> 0 | C15: =SUMIFS(Sales_Memo!$F$2:$F$1001,Sales_Memo!$B$2:$B$1001,">="&$A15,Sales_Memo!$B$2:$B$1001,"<"&DATE(YEAR($A15),MONTH($A15)+1,1)) -> 0 | D15: =B15-C15 -> 0 | E15: =SUMIFS(Sales_Items!$I$2:$I$3001,Sales_Items!$B$2:$B$3001,">="&$A15,Sales_Items!$B$2:$B$3001,"<"&DATE(YEAR($A15),MONTH($A15)+1,1)) -> 0 | F15: =D15-E15 -> 0 | G15: =SUMIFS(Running_Costs!$D$2:$D$1001,Running_Costs!$A$2:$A$1001,">="&$A15,Running_Costs!$A$2:$A$1001,"<"&DATE(YEAR($A15),MONTH($A15)+1,1)) -> 0 | H15: =F15-G15 -> 0 | I15: =SUMIFS(Fixed_Costs!$D$2:$D$501,Fixed_Costs!$A$2:$A$501,">="&$A15,Fixed_Costs!$A$2:$A$501,"<"&DATE(YEAR($A15),MONTH($A15)+1,1)) -> 0 | J15: =H15-I15 -> 0
A16: =DATE(Settings!$B$9,12,1) -> 46357 | B16: =SUMIFS(Sales_Items!$H$2:$H$3001,Sales_Items!$B$2:$B$3001,">="&$A16,Sales_Items!$B$2:$B$3001,"<"&DATE(YEAR($A16),MONTH($A16)+1,1)) -> 0 | C16: =SUMIFS(Sales_Memo!$F$2:$F$1001,Sales_Memo!$B$2:$B$1001,">="&$A16,Sales_Memo!$B$2:$B$1001,"<"&DATE(YEAR($A16),MONTH($A16)+1,1)) -> 0 | D16: =B16-C16 -> 0 | E16: =SUMIFS(Sales_Items!$I$2:$I$3001,Sales_Items!$B$2:$B$3001,">="&$A16,Sales_Items!$B$2:$B$3001,"<"&DATE(YEAR($A16),MONTH($A16)+1,1)) -> 0 | F16: =D16-E16 -> 0 | G16: =SUMIFS(Running_Costs!$D$2:$D$1001,Running_Costs!$A$2:$A$1001,">="&$A16,Running_Costs!$A$2:$A$1001,"<"&DATE(YEAR($A16),MONTH($A16)+1,1)) -> 0 | H16: =F16-G16 -> 0 | I16: =SUMIFS(Fixed_Costs!$D$2:$D$501,Fixed_Costs!$A$2:$A$501,">="&$A16,Fixed_Costs!$A$2:$A$501,"<"&DATE(YEAR($A16),MONTH($A16)+1,1)) -> 0 | J16: =H16-I16 -> 0
A17: TOTAL | B17: =SUM(B5:B16) -> 785010 | C17: =SUM(C5:C16) -> 15410 | D17: =SUM(D5:D16) -> 769600 | E17: =SUM(E5:E16) -> 537940 | F17: =SUM(F5:F16) -> 231660 | G17: =SUM(G5:G16) -> 152204 | H17: =SUM(H5:H16) -> 79456 | I17: =SUM(I5:I16) -> 243000 | J17: =SUM(J5:J16) -> -163544
A21: YEARLY (5 years from first year in Settings)
A22: Period | B22: Gross Sales | C22: Discounts | D22: Net Sales | E22: Cost of Goods Sold | F22: Gross Profit | G22: Running Costs | H22: OPERATING PROFIT | I22: Fixed Costs | J22: Result after Fixed Costs
A23: =Settings!$B$11 -> 2026 | B23: =SUMIFS(Sales_Items!$H$2:$H$3001,Sales_Items!$B$2:$B$3001,">="&DATE($A23,1,1),Sales_Items!$B$2:$B$3001,"<"&DATE($A23+1,1,1)) -> 785010 | C23: =SUMIFS(Sales_Memo!$F$2:$F$1001,Sales_Memo!$B$2:$B$1001,">="&DATE($A23,1,1),Sales_Memo!$B$2:$B$1001,"<"&DATE($A23+1,1,1)) -> 15410 | D23: =B23-C23 -> 769600 | E23: =SUMIFS(Sales_Items!$I$2:$I$3001,Sales_Items!$B$2:$B$3001,">="&DATE($A23,1,1),Sales_Items!$B$2:$B$3001,"<"&DATE($A23+1,1,1)) -> 537940 | F23: =D23-E23 -> 231660 | G23: =SUMIFS(Running_Costs!$D$2:$D$1001,Running_Costs!$A$2:$A$1001,">="&DATE($A23,1,1),Running_Costs!$A$2:$A$1001,"<"&DATE($A23+1,1,1)) -> 152204 | H23: =F23-G23 -> 79456 | I23: =SUMIFS(Fixed_Costs!$D$2:$D$501,Fixed_Costs!$A$2:$A$501,">="&DATE($A23,1,1),Fixed_Costs!$A$2:$A$501,"<"&DATE($A23+1,1,1)) -> 243000 | J23: =H23-I23 -> -163544
A24: =A23+1 -> 2027 | B24: =SUMIFS(Sales_Items!$H$2:$H$3001,Sales_Items!$B$2:$B$3001,">="&DATE($A24,1,1),Sales_Items!$B$2:$B$3001,"<"&DATE($A24+1,1,1)) -> 0 | C24: =SUMIFS(Sales_Memo!$F$2:$F$1001,Sales_Memo!$B$2:$B$1001,">="&DATE($A24,1,1),Sales_Memo!$B$2:$B$1001,"<"&DATE($A24+1,1,1)) -> 0 | D24: =B24-C24 -> 0 | E24: =SUMIFS(Sales_Items!$I$2:$I$3001,Sales_Items!$B$2:$B$3001,">="&DATE($A24,1,1),Sales_Items!$B$2:$B$3001,"<"&DATE($A24+1,1,1)) -> 0 | F24: =D24-E24 -> 0 | G24: =SUMIFS(Running_Costs!$D$2:$D$1001,Running_Costs!$A$2:$A$1001,">="&DATE($A24,1,1),Running_Costs!$A$2:$A$1001,"<"&DATE($A24+1,1,1)) -> 0 | H24: =F24-G24 -> 0 | I24: =SUMIFS(Fixed_Costs!$D$2:$D$501,Fixed_Costs!$A$2:$A$501,">="&DATE($A24,1,1),Fixed_Costs!$A$2:$A$501,"<"&DATE($A24+1,1,1)) -> 0 | J24: =H24-I24 -> 0
A25: =A24+1 -> 2028 | B25: =SUMIFS(Sales_Items!$H$2:$H$3001,Sales_Items!$B$2:$B$3001,">="&DATE($A25,1,1),Sales_Items!$B$2:$B$3001,"<"&DATE($A25+1,1,1)) -> 0 | C25: =SUMIFS(Sales_Memo!$F$2:$F$1001,Sales_Memo!$B$2:$B$1001,">="&DATE($A25,1,1),Sales_Memo!$B$2:$B$1001,"<"&DATE($A25+1,1,1)) -> 0 | D25: =B25-C25 -> 0 | E25: =SUMIFS(Sales_Items!$I$2:$I$3001,Sales_Items!$B$2:$B$3001,">="&DATE($A25,1,1),Sales_Items!$B$2:$B$3001,"<"&DATE($A25+1,1,1)) -> 0 | F25: =D25-E25 -> 0 | G25: =SUMIFS(Running_Costs!$D$2:$D$1001,Running_Costs!$A$2:$A$1001,">="&DATE($A25,1,1),Running_Costs!$A$2:$A$1001,"<"&DATE($A25+1,1,1)) -> 0 | H25: =F25-G25 -> 0 | I25: =SUMIFS(Fixed_Costs!$D$2:$D$501,Fixed_Costs!$A$2:$A$501,">="&DATE($A25,1,1),Fixed_Costs!$A$2:$A$501,"<"&DATE($A25+1,1,1)) -> 0 | J25: =H25-I25 -> 0
A26: =A25+1 -> 2029 | B26: =SUMIFS(Sales_Items!$H$2:$H$3001,Sales_Items!$B$2:$B$3001,">="&DATE($A26,1,1),Sales_Items!$B$2:$B$3001,"<"&DATE($A26+1,1,1)) -> 0 | C26: =SUMIFS(Sales_Memo!$F$2:$F$1001,Sales_Memo!$B$2:$B$1001,">="&DATE($A26,1,1),Sales_Memo!$B$2:$B$1001,"<"&DATE($A26+1,1,1)) -> 0 | D26: =B26-C26 -> 0 | E26: =SUMIFS(Sales_Items!$I$2:$I$3001,Sales_Items!$B$2:$B$3001,">="&DATE($A26,1,1),Sales_Items!$B$2:$B$3001,"<"&DATE($A26+1,1,1)) -> 0 | F26: =D26-E26 -> 0 | G26: =SUMIFS(Running_Costs!$D$2:$D$1001,Running_Costs!$A$2:$A$1001,">="&DATE($A26,1,1),Running_Costs!$A$2:$A$1001,"<"&DATE($A26+1,1,1)) -> 0 | H26: =F26-G26 -> 0 | I26: =SUMIFS(Fixed_Costs!$D$2:$D$501,Fixed_Costs!$A$2:$A$501,">="&DATE($A26,1,1),Fixed_Costs!$A$2:$A$501,"<"&DATE($A26+1,1,1)) -> 0 | J26: =H26-I26 -> 0
A27: =A26+1 -> 2030 | B27: =SUMIFS(Sales_Items!$H$2:$H$3001,Sales_Items!$B$2:$B$3001,">="&DATE($A27,1,1),Sales_Items!$B$2:$B$3001,"<"&DATE($A27+1,1,1)) -> 0 | C27: =SUMIFS(Sales_Memo!$F$2:$F$1001,Sales_Memo!$B$2:$B$1001,">="&DATE($A27,1,1),Sales_Memo!$B$2:$B$1001,"<"&DATE($A27+1,1,1)) -> 0 | D27: =B27-C27 -> 0 | E27: =SUMIFS(Sales_Items!$I$2:$I$3001,Sales_Items!$B$2:$B$3001,">="&DATE($A27,1,1),Sales_Items!$B$2:$B$3001,"<"&DATE($A27+1,1,1)) -> 0 | F27: =D27-E27 -> 0 | G27: =SUMIFS(Running_Costs!$D$2:$D$1001,Running_Costs!$A$2:$A$1001,">="&DATE($A27,1,1),Running_Costs!$A$2:$A$1001,"<"&DATE($A27+1,1,1)) -> 0 | H27: =F27-G27 -> 0 | I27: =SUMIFS(Fixed_Costs!$D$2:$D$501,Fixed_Costs!$A$2:$A$501,">="&DATE($A27,1,1),Fixed_Costs!$A$2:$A$501,"<"&DATE($A27+1,1,1)) -> 0 | J27: =H27-I27 -> 0
A28: TOTAL | B28: =SUM(B23:B27) -> 785010 | C28: =SUM(C23:C27) -> 15410 | D28: =SUM(D23:D27) -> 769600 | E28: =SUM(E23:E27) -> 537940 | F28: =SUM(F23:F27) -> 231660 | G28: =SUM(G23:G27) -> 152204 | H28: =SUM(H23:H27) -> 79456 | I28: =SUM(I23:I27) -> 243000 | J28: =SUM(J23:J27) -> -163544
A30: WEEKLY (last 12 weeks, week starts Monday)
A31: Period | B31: Gross Sales | C31: Discounts | D31: Net Sales | E31: Cost of Goods Sold | F31: Gross Profit | G31: Running Costs | H31: OPERATING PROFIT | I31: Fixed Costs | J31: Result after Fixed Costs
A32: =TODAY()-WEEKDAY(TODAY(),2)+1-7*11 -> 46237 | B32: =SUMIFS(Sales_Items!$H$2:$H$3001,Sales_Items!$B$2:$B$3001,">="&$A32,Sales_Items!$B$2:$B$3001,"<"&($A32+7)) -> 63130 | C32: =SUMIFS(Sales_Memo!$F$2:$F$1001,Sales_Memo!$B$2:$B$1001,">="&$A32,Sales_Memo!$B$2:$B$1001,"<"&($A32+7)) -> 1110 | D32: =B32-C32 -> 62020 | E32: =SUMIFS(Sales_Items!$I$2:$I$3001,Sales_Items!$B$2:$B$3001,">="&$A32,Sales_Items!$B$2:$B$3001,"<"&($A32+7)) -> 43710 | F32: =D32-E32 -> 18310 | G32: =SUMIFS(Running_Costs!$D$2:$D$1001,Running_Costs!$A$2:$A$1001,">="&$A32,Running_Costs!$A$2:$A$1001,"<"&($A32+7)) -> 20000 | H32: =F32-G32 -> -1690 | I32: =SUMIFS(Fixed_Costs!$D$2:$D$501,Fixed_Costs!$A$2:$A$501,">="&$A32,Fixed_Costs!$A$2:$A$501,"<"&($A32+7)) -> 0 | J32: =H32-I32 -> -1690
A33: =TODAY()-WEEKDAY(TODAY(),2)+1-7*10 -> 46244 | B33: =SUMIFS(Sales_Items!$H$2:$H$3001,Sales_Items!$B$2:$B$3001,">="&$A33,Sales_Items!$B$2:$B$3001,"<"&($A33+7)) -> 70130 | C33: =SUMIFS(Sales_Memo!$F$2:$F$1001,Sales_Memo!$B$2:$B$1001,">="&$A33,Sales_Memo!$B$2:$B$1001,"<"&($A33+7)) -> 1370 | D33: =B33-C33 -> 68760 | E33: =SUMIFS(Sales_Items!$I$2:$I$3001,Sales_Items!$B$2:$B$3001,">="&$A33,Sales_Items!$B$2:$B$3001,"<"&($A33+7)) -> 47200 | F33: =D33-E33 -> 21560 | G33: =SUMIFS(Running_Costs!$D$2:$D$1001,Running_Costs!$A$2:$A$1001,">="&$A33,Running_Costs!$A$2:$A$1001,"<"&($A33+7)) -> 5773 | H33: =F33-G33 -> 15787 | I33: =SUMIFS(Fixed_Costs!$D$2:$D$501,Fixed_Costs!$A$2:$A$501,">="&$A33,Fixed_Costs!$A$2:$A$501,"<"&($A33+7)) -> 0 | J33: =H33-I33 -> 15787
A34: =TODAY()-WEEKDAY(TODAY(),2)+1-7*9 -> 46251 | B34: =SUMIFS(Sales_Items!$H$2:$H$3001,Sales_Items!$B$2:$B$3001,">="&$A34,Sales_Items!$B$2:$B$3001,"<"&($A34+7)) -> 63330 | C34: =SUMIFS(Sales_Memo!$F$2:$F$1001,Sales_Memo!$B$2:$B$1001,">="&$A34,Sales_Memo!$B$2:$B$1001,"<"&($A34+7)) -> 740 | D34: =B34-C34 -> 62590 | E34: =SUMIFS(Sales_Items!$I$2:$I$3001,Sales_Items!$B$2:$B$3001,">="&$A34,Sales_Items!$B$2:$B$3001,"<"&($A34+7)) -> 43915 | F34: =D34-E34 -> 18675 | G34: =SUMIFS(Running_Costs!$D$2:$D$1001,Running_Costs!$A$2:$A$1001,">="&$A34,Running_Costs!$A$2:$A$1001,"<"&($A34+7)) -> 660 | H34: =F34-G34 -> 18015 | I34: =SUMIFS(Fixed_Costs!$D$2:$D$501,Fixed_Costs!$A$2:$A$501,">="&$A34,Fixed_Costs!$A$2:$A$501,"<"&($A34+7)) -> 0 | J34: =H34-I34 -> 18015
A35: =TODAY()-WEEKDAY(TODAY(),2)+1-7*8 -> 46258 | B35: =SUMIFS(Sales_Items!$H$2:$H$3001,Sales_Items!$B$2:$B$3001,">="&$A35,Sales_Items!$B$2:$B$3001,"<"&($A35+7)) -> 60830 | C35: =SUMIFS(Sales_Memo!$F$2:$F$1001,Sales_Memo!$B$2:$B$1001,">="&$A35,Sales_Memo!$B$2:$B$1001,"<"&($A35+7)) -> 1010 | D35: =B35-C35 -> 59820 | E35: =SUMIFS(Sales_Items!$I$2:$I$3001,Sales_Items!$B$2:$B$3001,">="&$A35,Sales_Items!$B$2:$B$3001,"<"&($A35+7)) -> 42480 | F35: =D35-E35 -> 17340 | G35: =SUMIFS(Running_Costs!$D$2:$D$1001,Running_Costs!$A$2:$A$1001,">="&$A35,Running_Costs!$A$2:$A$1001,"<"&($A35+7)) -> 0 | H35: =F35-G35 -> 17340 | I35: =SUMIFS(Fixed_Costs!$D$2:$D$501,Fixed_Costs!$A$2:$A$501,">="&$A35,Fixed_Costs!$A$2:$A$501,"<"&($A35+7)) -> 0 | J35: =H35-I35 -> 17340
A36: =TODAY()-WEEKDAY(TODAY(),2)+1-7*7 -> 46265 | B36: =SUMIFS(Sales_Items!$H$2:$H$3001,Sales_Items!$B$2:$B$3001,">="&$A36,Sales_Items!$B$2:$B$3001,"<"&($A36+7)) -> 65750 | C36: =SUMIFS(Sales_Memo!$F$2:$F$1001,Sales_Memo!$B$2:$B$1001,">="&$A36,Sales_Memo!$B$2:$B$1001,"<"&($A36+7)) -> 970 | D36: =B36-C36 -> 64780 | E36: =SUMIFS(Sales_Items!$I$2:$I$3001,Sales_Items!$B$2:$B$3001,">="&$A36,Sales_Items!$B$2:$B$3001,"<"&($A36+7)) -> 45910 | F36: =D36-E36 -> 18870 | G36: =SUMIFS(Running_Costs!$D$2:$D$1001,Running_Costs!$A$2:$A$1001,">="&$A36,Running_Costs!$A$2:$A$1001,"<"&($A36+7)) -> 44000 | H36: =F36-G36 -> -25130 | I36: =SUMIFS(Fixed_Costs!$D$2:$D$501,Fixed_Costs!$A$2:$A$501,">="&$A36,Fixed_Costs!$A$2:$A$501,"<"&($A36+7)) -> 0 | J36: =H36-I36 -> -25130
A37: =TODAY()-WEEKDAY(TODAY(),2)+1-7*6 -> 46272 | B37: =SUMIFS(Sales_Items!$H$2:$H$3001,Sales_Items!$B$2:$B$3001,">="&$A37,Sales_Items!$B$2:$B$3001,"<"&($A37+7)) -> 68090 | C37: =SUMIFS(Sales_Memo!$F$2:$F$1001,Sales_Memo!$B$2:$B$1001,">="&$A37,Sales_Memo!$B$2:$B$1001,"<"&($A37+7)) -> 1630 | D37: =B37-C37 -> 66460 | E37: =SUMIFS(Sales_Items!$I$2:$I$3001,Sales_Items!$B$2:$B$3001,">="&$A37,Sales_Items!$B$2:$B$3001,"<"&($A37+7)) -> 46330 | F37: =D37-E37 -> 20130 | G37: =SUMIFS(Running_Costs!$D$2:$D$1001,Running_Costs!$A$2:$A$1001,">="&$A37,Running_Costs!$A$2:$A$1001,"<"&($A37+7)) -> 3979 | H37: =F37-G37 -> 16151 | I37: =SUMIFS(Fixed_Costs!$D$2:$D$501,Fixed_Costs!$A$2:$A$501,">="&$A37,Fixed_Costs!$A$2:$A$501,"<"&($A37+7)) -> 0 | J37: =H37-I37 -> 16151
A38: =TODAY()-WEEKDAY(TODAY(),2)+1-7*5 -> 46279 | B38: =SUMIFS(Sales_Items!$H$2:$H$3001,Sales_Items!$B$2:$B$3001,">="&$A38,Sales_Items!$B$2:$B$3001,"<"&($A38+7)) -> 68500 | C38: =SUMIFS(Sales_Memo!$F$2:$F$1001,Sales_Memo!$B$2:$B$1001,">="&$A38,Sales_Memo!$B$2:$B$1001,"<"&($A38+7)) -> 1640 | D38: =B38-C38 -> 66860 | E38: =SUMIFS(Sales_Items!$I$2:$I$3001,Sales_Items!$B$2:$B$3001,">="&$A38,Sales_Items!$B$2:$B$3001,"<"&($A38+7)) -> 46900 | F38: =D38-E38 -> 19960 | G38: =SUMIFS(Running_Costs!$D$2:$D$1001,Running_Costs!$A$2:$A$1001,">="&$A38,Running_Costs!$A$2:$A$1001,"<"&($A38+7)) -> 3612 | H38: =F38-G38 -> 16348 | I38: =SUMIFS(Fixed_Costs!$D$2:$D$501,Fixed_Costs!$A$2:$A$501,">="&$A38,Fixed_Costs!$A$2:$A$501,"<"&($A38+7)) -> 0 | J38: =H38-I38 -> 16348
A39: =TODAY()-WEEKDAY(TODAY(),2)+1-7*4 -> 46286 | B39: =SUMIFS(Sales_Items!$H$2:$H$3001,Sales_Items!$B$2:$B$3001,">="&$A39,Sales_Items!$B$2:$B$3001,"<"&($A39+7)) -> 67430 | C39: =SUMIFS(Sales_Memo!$F$2:$F$1001,Sales_Memo!$B$2:$B$1001,">="&$A39,Sales_Memo!$B$2:$B$1001,"<"&($A39+7)) -> 1270 | D39: =B39-C39 -> 66160 | E39: =SUMIFS(Sales_Items!$I$2:$I$3001,Sales_Items!$B$2:$B$3001,">="&$A39,Sales_Items!$B$2:$B$3001,"<"&($A39+7)) -> 45545 | F39: =D39-E39 -> 20615 | G39: =SUMIFS(Running_Costs!$D$2:$D$1001,Running_Costs!$A$2:$A$1001,">="&$A39,Running_Costs!$A$2:$A$1001,"<"&($A39+7)) -> 0 | H39: =F39-G39 -> 20615 | I39: =SUMIFS(Fixed_Costs!$D$2:$D$501,Fixed_Costs!$A$2:$A$501,">="&$A39,Fixed_Costs!$A$2:$A$501,"<"&($A39+7)) -> 0 | J39: =H39-I39 -> 20615
A40: =TODAY()-WEEKDAY(TODAY(),2)+1-7*3 -> 46293 | B40: =SUMIFS(Sales_Items!$H$2:$H$3001,Sales_Items!$B$2:$B$3001,">="&$A40,Sales_Items!$B$2:$B$3001,"<"&($A40+7)) -> 59130 | C40: =SUMIFS(Sales_Memo!$F$2:$F$1001,Sales_Memo!$B$2:$B$1001,">="&$A40,Sales_Memo!$B$2:$B$1001,"<"&($A40+7)) -> 1170 | D40: =B40-C40 -> 57960 | E40: =SUMIFS(Sales_Items!$I$2:$I$3001,Sales_Items!$B$2:$B$3001,">="&$A40,Sales_Items!$B$2:$B$3001,"<"&($A40+7)) -> 40140 | F40: =D40-E40 -> 17820 | G40: =SUMIFS(Running_Costs!$D$2:$D$1001,Running_Costs!$A$2:$A$1001,">="&$A40,Running_Costs!$A$2:$A$1001,"<"&($A40+7)) -> 24000 | H40: =F40-G40 -> -6180 | I40: =SUMIFS(Fixed_Costs!$D$2:$D$501,Fixed_Costs!$A$2:$A$501,">="&$A40,Fixed_Costs!$A$2:$A$501,"<"&($A40+7)) -> 0 | J40: =H40-I40 -> -6180
A41: =TODAY()-WEEKDAY(TODAY(),2)+1-7*2 -> 46300 | B41: =SUMIFS(Sales_Items!$H$2:$H$3001,Sales_Items!$B$2:$B$3001,">="&$A41,Sales_Items!$B$2:$B$3001,"<"&($A41+7)) -> 76600 | C41: =SUMIFS(Sales_Memo!$F$2:$F$1001,Sales_Memo!$B$2:$B$1001,">="&$A41,Sales_Memo!$B$2:$B$1001,"<"&($A41+7)) -> 1390 | D41: =B41-C41 -> 75210 | E41: =SUMIFS(Sales_Items!$I$2:$I$3001,Sales_Items!$B$2:$B$3001,">="&$A41,Sales_Items!$B$2:$B$3001,"<"&($A41+7)) -> 53555 | F41: =D41-E41 -> 21655 | G41: =SUMIFS(Running_Costs!$D$2:$D$1001,Running_Costs!$A$2:$A$1001,">="&$A41,Running_Costs!$A$2:$A$1001,"<"&($A41+7)) -> 21000 | H41: =F41-G41 -> 655 | I41: =SUMIFS(Fixed_Costs!$D$2:$D$501,Fixed_Costs!$A$2:$A$501,">="&$A41,Fixed_Costs!$A$2:$A$501,"<"&($A41+7)) -> 0 | J41: =H41-I41 -> 655
A42: =TODAY()-WEEKDAY(TODAY(),2)+1-7*1 -> 46307 | B42: =SUMIFS(Sales_Items!$H$2:$H$3001,Sales_Items!$B$2:$B$3001,">="&$A42,Sales_Items!$B$2:$B$3001,"<"&($A42+7)) -> 69690 | C42: =SUMIFS(Sales_Memo!$F$2:$F$1001,Sales_Memo!$B$2:$B$1001,">="&$A42,Sales_Memo!$B$2:$B$1001,"<"&($A42+7)) -> 1870 | D42: =B42-C42 -> 67820 | E42: =SUMIFS(Sales_Items!$I$2:$I$3001,Sales_Items!$B$2:$B$3001,">="&$A42,Sales_Items!$B$2:$B$3001,"<"&($A42+7)) -> 45985 | F42: =D42-E42 -> 21835 | G42: =SUMIFS(Running_Costs!$D$2:$D$1001,Running_Costs!$A$2:$A$1001,">="&$A42,Running_Costs!$A$2:$A$1001,"<"&($A42+7)) -> 5180 | H42: =F42-G42 -> 16655 | I42: =SUMIFS(Fixed_Costs!$D$2:$D$501,Fixed_Costs!$A$2:$A$501,">="&$A42,Fixed_Costs!$A$2:$A$501,"<"&($A42+7)) -> 0 | J42: =H42-I42 -> 16655
A43: =TODAY()-WEEKDAY(TODAY(),2)+1-7*0 -> 46314 | B43: =SUMIFS(Sales_Items!$H$2:$H$3001,Sales_Items!$B$2:$B$3001,">="&$A43,Sales_Items!$B$2:$B$3001,"<"&($A43+7)) -> 52400 | C43: =SUMIFS(Sales_Memo!$F$2:$F$1001,Sales_Memo!$B$2:$B$1001,">="&$A43,Sales_Memo!$B$2:$B$1001,"<"&($A43+7)) -> 1240 | D43: =B43-C43 -> 51160 | E43: =SUMIFS(Sales_Items!$I$2:$I$3001,Sales_Items!$B$2:$B$3001,">="&$A43,Sales_Items!$B$2:$B$3001,"<"&($A43+7)) -> 36270 | F43: =D43-E43 -> 14890 | G43: =SUMIFS(Running_Costs!$D$2:$D$1001,Running_Costs!$A$2:$A$1001,">="&$A43,Running_Costs!$A$2:$A$1001,"<"&($A43+7)) -> 0 | H43: =F43-G43 -> 14890 | I43: =SUMIFS(Fixed_Costs!$D$2:$D$501,Fixed_Costs!$A$2:$A$501,">="&$A43,Fixed_Costs!$A$2:$A$501,"<"&($A43+7)) -> 0 | J43: =H43-I43 -> 14890

Sheet Reinvestment
A1: CASH FLOW & REINVESTMENT (report year)
A2: Reinvested (gross) = stock purchases + fixed-cost spending. Net inventory growth = purchases minus cost of goods sold (real stock build-up). Profit kept = Operating Profit - Owner Drawings.
A4: Month | B4: Cash from Sales (paid at sale) | C4: Dues Collected | D4: Capital Added by Owner | E4: TOTAL CASH IN | F4: Stock Purchases | G4: Running Costs | H4: Fixed Costs | I4: Owner Drawings | J4: TOTAL CASH OUT | K4: Net Cash Change | L4: Closing Cash | M4: Reinvested (gross) | N4: Net Inventory Growth | O4: Reinvestment Rate (of Net Sales) | P4: Profit Kept (Op. Profit - Drawings)
A5: =DATE(Settings!$B$9,1,1) -> 46023 | B5: =SUMIFS(Sales_Memo!$H$2:$H$1001,Sales_Memo!$B$2:$B$1001,">="&$A5,Sales_Memo!$B$2:$B$1001,"<"&DATE(YEAR($A5),MONTH($A5)+1,1)) -> 0 | C5: =SUMIFS(Due_Payments!$C$2:$C$1001,Due_Payments!$A$2:$A$1001,">="&$A5,Due_Payments!$A$2:$A$1001,"<"&DATE(YEAR($A5),MONTH($A5)+1,1)) -> 0 | D5: =SUMIFS(Owner_Capital!$C$2:$C$501,Owner_Capital!$B$2:$B$501,"Capital In",Owner_Capital!$A$2:$A$501,">="&$A5,Owner_Capital!$A$2:$A$501,"<"&DATE(YEAR($A5),MONTH($A5)+1,1)) -> 0 | E5: =SUM(B5:D5) -> 0 | F5: =SUMIFS(Purchases!$F$2:$F$2001,Purchases!$A$2:$A$2001,">="&$A5,Purchases!$A$2:$A$2001,"<"&DATE(YEAR($A5),MONTH($A5)+1,1)) -> 0 | G5: =SUMIFS(Running_Costs!$D$2:$D$1001,Running_Costs!$A$2:$A$1001,">="&$A5,Running_Costs!$A$2:$A$1001,"<"&DATE(YEAR($A5),MONTH($A5)+1,1)) -> 0 | H5: =SUMIFS(Fixed_Costs!$D$2:$D$501,Fixed_Costs!$A$2:$A$501,">="&$A5,Fixed_Costs!$A$2:$A$501,"<"&DATE(YEAR($A5),MONTH($A5)+1,1)) -> 0 | I5: =SUMIFS(Owner_Capital!$C$2:$C$501,Owner_Capital!$B$2:$B$501,"Owner Drawing",Owner_Capital!$A$2:$A$501,">="&$A5,Owner_Capital!$A$2:$A$501,"<"&DATE(YEAR($A5),MONTH($A5)+1,1)) -> 0 | J5: =SUM(F5:I5) -> 0 | K5: =E5-J5 -> 0 | L5: =Settings!$B$10+K5 -> 0 | M5: =F5+H5 -> 0 | N5: =F5-Profit!E5 -> 0 | O5: =IF(Profit!D5=0,0,M5/Profit!D5) -> 0 | P5: =Profit!H5-I5 -> 0
A6: =DATE(Settings!$B$9,2,1) -> 46054 | B6: =SUMIFS(Sales_Memo!$H$2:$H$1001,Sales_Memo!$B$2:$B$1001,">="&$A6,Sales_Memo!$B$2:$B$1001,"<"&DATE(YEAR($A6),MONTH($A6)+1,1)) -> 0 | C6: =SUMIFS(Due_Payments!$C$2:$C$1001,Due_Payments!$A$2:$A$1001,">="&$A6,Due_Payments!$A$2:$A$1001,"<"&DATE(YEAR($A6),MONTH($A6)+1,1)) -> 0 | D6: =SUMIFS(Owner_Capital!$C$2:$C$501,Owner_Capital!$B$2:$B$501,"Capital In",Owner_Capital!$A$2:$A$501,">="&$A6,Owner_Capital!$A$2:$A$501,"<"&DATE(YEAR($A6),MONTH($A6)+1,1)) -> 0 | E6: =SUM(B6:D6) -> 0 | F6: =SUMIFS(Purchases!$F$2:$F$2001,Purchases!$A$2:$A$2001,">="&$A6,Purchases!$A$2:$A$2001,"<"&DATE(YEAR($A6),MONTH($A6)+1,1)) -> 0 | G6: =SUMIFS(Running_Costs!$D$2:$D$1001,Running_Costs!$A$2:$A$1001,">="&$A6,Running_Costs!$A$2:$A$1001,"<"&DATE(YEAR($A6),MONTH($A6)+1,1)) -> 0 | H6: =SUMIFS(Fixed_Costs!$D$2:$D$501,Fixed_Costs!$A$2:$A$501,">="&$A6,Fixed_Costs!$A$2:$A$501,"<"&DATE(YEAR($A6),MONTH($A6)+1,1)) -> 0 | I6: =SUMIFS(Owner_Capital!$C$2:$C$501,Owner_Capital!$B$2:$B$501,"Owner Drawing",Owner_Capital!$A$2:$A$501,">="&$A6,Owner_Capital!$A$2:$A$501,"<"&DATE(YEAR($A6),MONTH($A6)+1,1)) -> 0 | J6: =SUM(F6:I6) -> 0 | K6: =E6-J6 -> 0 | L6: =L5+K6 -> 0 | M6: =F6+H6 -> 0 | N6: =F6-Profit!E6 -> 0 | O6: =IF(Profit!D6=0,0,M6/Profit!D6) -> 0 | P6: =Profit!H6-I6 -> 0
A7: =DATE(Settings!$B$9,3,1) -> 46082 | B7: =SUMIFS(Sales_Memo!$H$2:$H$1001,Sales_Memo!$B$2:$B$1001,">="&$A7,Sales_Memo!$B$2:$B$1001,"<"&DATE(YEAR($A7),MONTH($A7)+1,1)) -> 0 | C7: =SUMIFS(Due_Payments!$C$2:$C$1001,Due_Payments!$A$2:$A$1001,">="&$A7,Due_Payments!$A$2:$A$1001,"<"&DATE(YEAR($A7),MONTH($A7)+1,1)) -> 0 | D7: =SUMIFS(Owner_Capital!$C$2:$C$501,Owner_Capital!$B$2:$B$501,"Capital In",Owner_Capital!$A$2:$A$501,">="&$A7,Owner_Capital!$A$2:$A$501,"<"&DATE(YEAR($A7),MONTH($A7)+1,1)) -> 0 | E7: =SUM(B7:D7) -> 0 | F7: =SUMIFS(Purchases!$F$2:$F$2001,Purchases!$A$2:$A$2001,">="&$A7,Purchases!$A$2:$A$2001,"<"&DATE(YEAR($A7),MONTH($A7)+1,1)) -> 0 | G7: =SUMIFS(Running_Costs!$D$2:$D$1001,Running_Costs!$A$2:$A$1001,">="&$A7,Running_Costs!$A$2:$A$1001,"<"&DATE(YEAR($A7),MONTH($A7)+1,1)) -> 0 | H7: =SUMIFS(Fixed_Costs!$D$2:$D$501,Fixed_Costs!$A$2:$A$501,">="&$A7,Fixed_Costs!$A$2:$A$501,"<"&DATE(YEAR($A7),MONTH($A7)+1,1)) -> 0 | I7: =SUMIFS(Owner_Capital!$C$2:$C$501,Owner_Capital!$B$2:$B$501,"Owner Drawing",Owner_Capital!$A$2:$A$501,">="&$A7,Owner_Capital!$A$2:$A$501,"<"&DATE(YEAR($A7),MONTH($A7)+1,1)) -> 0 | J7: =SUM(F7:I7) -> 0 | K7: =E7-J7 -> 0 | L7: =L6+K7 -> 0 | M7: =F7+H7 -> 0 | N7: =F7-Profit!E7 -> 0 | O7: =IF(Profit!D7=0,0,M7/Profit!D7) -> 0 | P7: =Profit!H7-I7 -> 0
A8: =DATE(Settings!$B$9,4,1) -> 46113 | B8: =SUMIFS(Sales_Memo!$H$2:$H$1001,Sales_Memo!$B$2:$B$1001,">="&$A8,Sales_Memo!$B$2:$B$1001,"<"&DATE(YEAR($A8),MONTH($A8)+1,1)) -> 0 | C8: =SUMIFS(Due_Payments!$C$2:$C$1001,Due_Payments!$A$2:$A$1001,">="&$A8,Due_Payments!$A$2:$A$1001,"<"&DATE(YEAR($A8),MONTH($A8)+1,1)) -> 0 | D8: =SUMIFS(Owner_Capital!$C$2:$C$501,Owner_Capital!$B$2:$B$501,"Capital In",Owner_Capital!$A$2:$A$501,">="&$A8,Owner_Capital!$A$2:$A$501,"<"&DATE(YEAR($A8),MONTH($A8)+1,1)) -> 0 | E8: =SUM(B8:D8) -> 0 | F8: =SUMIFS(Purchases!$F$2:$F$2001,Purchases!$A$2:$A$2001,">="&$A8,Purchases!$A$2:$A$2001,"<"&DATE(YEAR($A8),MONTH($A8)+1,1)) -> 0 | G8: =SUMIFS(Running_Costs!$D$2:$D$1001,Running_Costs!$A$2:$A$1001,">="&$A8,Running_Costs!$A$2:$A$1001,"<"&DATE(YEAR($A8),MONTH($A8)+1,1)) -> 0 | H8: =SUMIFS(Fixed_Costs!$D$2:$D$501,Fixed_Costs!$A$2:$A$501,">="&$A8,Fixed_Costs!$A$2:$A$501,"<"&DATE(YEAR($A8),MONTH($A8)+1,1)) -> 0 | I8: =SUMIFS(Owner_Capital!$C$2:$C$501,Owner_Capital!$B$2:$B$501,"Owner Drawing",Owner_Capital!$A$2:$A$501,">="&$A8,Owner_Capital!$A$2:$A$501,"<"&DATE(YEAR($A8),MONTH($A8)+1,1)) -> 0 | J8: =SUM(F8:I8) -> 0 | K8: =E8-J8 -> 0 | L8: =L7+K8 -> 0 | M8: =F8+H8 -> 0 | N8: =F8-Profit!E8 -> 0 | O8: =IF(Profit!D8=0,0,M8/Profit!D8) -> 0 | P8: =Profit!H8-I8 -> 0
A9: =DATE(Settings!$B$9,5,1) -> 46143 | B9: =SUMIFS(Sales_Memo!$H$2:$H$1001,Sales_Memo!$B$2:$B$1001,">="&$A9,Sales_Memo!$B$2:$B$1001,"<"&DATE(YEAR($A9),MONTH($A9)+1,1)) -> 0 | C9: =SUMIFS(Due_Payments!$C$2:$C$1001,Due_Payments!$A$2:$A$1001,">="&$A9,Due_Payments!$A$2:$A$1001,"<"&DATE(YEAR($A9),MONTH($A9)+1,1)) -> 0 | D9: =SUMIFS(Owner_Capital!$C$2:$C$501,Owner_Capital!$B$2:$B$501,"Capital In",Owner_Capital!$A$2:$A$501,">="&$A9,Owner_Capital!$A$2:$A$501,"<"&DATE(YEAR($A9),MONTH($A9)+1,1)) -> 0 | E9: =SUM(B9:D9) -> 0 | F9: =SUMIFS(Purchases!$F$2:$F$2001,Purchases!$A$2:$A$2001,">="&$A9,Purchases!$A$2:$A$2001,"<"&DATE(YEAR($A9),MONTH($A9)+1,1)) -> 0 | G9: =SUMIFS(Running_Costs!$D$2:$D$1001,Running_Costs!$A$2:$A$1001,">="&$A9,Running_Costs!$A$2:$A$1001,"<"&DATE(YEAR($A9),MONTH($A9)+1,1)) -> 0 | H9: =SUMIFS(Fixed_Costs!$D$2:$D$501,Fixed_Costs!$A$2:$A$501,">="&$A9,Fixed_Costs!$A$2:$A$501,"<"&DATE(YEAR($A9),MONTH($A9)+1,1)) -> 0 | I9: =SUMIFS(Owner_Capital!$C$2:$C$501,Owner_Capital!$B$2:$B$501,"Owner Drawing",Owner_Capital!$A$2:$A$501,">="&$A9,Owner_Capital!$A$2:$A$501,"<"&DATE(YEAR($A9),MONTH($A9)+1,1)) -> 0 | J9: =SUM(F9:I9) -> 0 | K9: =E9-J9 -> 0 | L9: =L8+K9 -> 0 | M9: =F9+H9 -> 0 | N9: =F9-Profit!E9 -> 0 | O9: =IF(Profit!D9=0,0,M9/Profit!D9) -> 0 | P9: =Profit!H9-I9 -> 0
A10: =DATE(Settings!$B$9,6,1) -> 46174 | B10: =SUMIFS(Sales_Memo!$H$2:$H$1001,Sales_Memo!$B$2:$B$1001,">="&$A10,Sales_Memo!$B$2:$B$1001,"<"&DATE(YEAR($A10),MONTH($A10)+1,1)) -> 0 | C10: =SUMIFS(Due_Payments!$C$2:$C$1001,Due_Payments!$A$2:$A$1001,">="&$A10,Due_Payments!$A$2:$A$1001,"<"&DATE(YEAR($A10),MONTH($A10)+1,1)) -> 0 | D10: =SUMIFS(Owner_Capital!$C$2:$C$501,Owner_Capital!$B$2:$B$501,"Capital In",Owner_Capital!$A$2:$A$501,">="&$A10,Owner_Capital!$A$2:$A$501,"<"&DATE(YEAR($A10),MONTH($A10)+1,1)) -> 0 | E10: =SUM(B10:D10) -> 0 | F10: =SUMIFS(Purchases!$F$2:$F$2001,Purchases!$A$2:$A$2001,">="&$A10,Purchases!$A$2:$A$2001,"<"&DATE(YEAR($A10),MONTH($A10)+1,1)) -> 0 | G10: =SUMIFS(Running_Costs!$D$2:$D$1001,Running_Costs!$A$2:$A$1001,">="&$A10,Running_Costs!$A$2:$A$1001,"<"&DATE(YEAR($A10),MONTH($A10)+1,1)) -> 0 | H10: =SUMIFS(Fixed_Costs!$D$2:$D$501,Fixed_Costs!$A$2:$A$501,">="&$A10,Fixed_Costs!$A$2:$A$501,"<"&DATE(YEAR($A10),MONTH($A10)+1,1)) -> 0 | I10: =SUMIFS(Owner_Capital!$C$2:$C$501,Owner_Capital!$B$2:$B$501,"Owner Drawing",Owner_Capital!$A$2:$A$501,">="&$A10,Owner_Capital!$A$2:$A$501,"<"&DATE(YEAR($A10),MONTH($A10)+1,1)) -> 0 | J10: =SUM(F10:I10) -> 0 | K10: =E10-J10 -> 0 | L10: =L9+K10 -> 0 | M10: =F10+H10 -> 0 | N10: =F10-Profit!E10 -> 0 | O10: =IF(Profit!D10=0,0,M10/Profit!D10) -> 0 | P10: =Profit!H10-I10 -> 0
A11: =DATE(Settings!$B$9,7,1) -> 46204 | B11: =SUMIFS(Sales_Memo!$H$2:$H$1001,Sales_Memo!$B$2:$B$1001,">="&$A11,Sales_Memo!$B$2:$B$1001,"<"&DATE(YEAR($A11),MONTH($A11)+1,1)) -> 0 | C11: =SUMIFS(Due_Payments!$C$2:$C$1001,Due_Payments!$A$2:$A$1001,">="&$A11,Due_Payments!$A$2:$A$1001,"<"&DATE(YEAR($A11),MONTH($A11)+1,1)) -> 0 | D11: =SUMIFS(Owner_Capital!$C$2:$C$501,Owner_Capital!$B$2:$B$501,"Capital In",Owner_Capital!$A$2:$A$501,">="&$A11,Owner_Capital!$A$2:$A$501,"<"&DATE(YEAR($A11),MONTH($A11)+1,1)) -> 300000 | E11: =SUM(B11:D11) -> 300000 | F11: =SUMIFS(Purchases!$F$2:$F$2001,Purchases!$A$2:$A$2001,">="&$A11,Purchases!$A$2:$A$2001,"<"&DATE(YEAR($A11),MONTH($A11)+1,1)) -> 0 | G11: =SUMIFS(Running_Costs!$D$2:$D$1001,Running_Costs!$A$2:$A$1001,">="&$A11,Running_Costs!$A$2:$A$1001,"<"&DATE(YEAR($A11),MONTH($A11)+1,1)) -> 0 | H11: =SUMIFS(Fixed_Costs!$D$2:$D$501,Fixed_Costs!$A$2:$A$501,">="&$A11,Fixed_Costs!$A$2:$A$501,"<"&DATE(YEAR($A11),MONTH($A11)+1,1)) -> 235000 | I11: =SUMIFS(Owner_Capital!$C$2:$C$501,Owner_Capital!$B$2:$B$501,"Owner Drawing",Owner_Capital!$A$2:$A$501,">="&$A11,Owner_Capital!$A$2:$A$501,"<"&DATE(YEAR($A11),MONTH($A11)+1,1)) -> 0 | J11: =SUM(F11:I11) -> 235000 | K11: =E11-J11 -> 65000 | L11: =L10+K11 -> 65000 | M11: =F11+H11 -> 235000 | N11: =F11-Profit!E11 -> 0 | O11: =IF(Profit!D11=0,0,M11/Profit!D11) -> 0 | P11: =Profit!H11-I11 -> 0
A12: =DATE(Settings!$B$9,8,1) -> 46235 | B12: =SUMIFS(Sales_Memo!$H$2:$H$1001,Sales_Memo!$B$2:$B$1001,">="&$A12,Sales_Memo!$B$2:$B$1001,"<"&DATE(YEAR($A12),MONTH($A12)+1,1)) -> 229190 | C12: =SUMIFS(Due_Payments!$C$2:$C$1001,Due_Payments!$A$2:$A$1001,">="&$A12,Due_Payments!$A$2:$A$1001,"<"&DATE(YEAR($A12),MONTH($A12)+1,1)) -> 11000 | D12: =SUMIFS(Owner_Capital!$C$2:$C$501,Owner_Capital!$B$2:$B$501,"Capital In",Owner_Capital!$A$2:$A$501,">="&$A12,Owner_Capital!$A$2:$A$501,"<"&DATE(YEAR($A12),MONTH($A12)+1,1)) -> 0 | E12: =SUM(B12:D12) -> 240190 | F12: =SUMIFS(Purchases!$F$2:$F$2001,Purchases!$A$2:$A$2001,">="&$A12,Purchases!$A$2:$A$2001,"<"&DATE(YEAR($A12),MONTH($A12)+1,1)) -> 61030 | G12: =SUMIFS(Running_Costs!$D$2:$D$1001,Running_Costs!$A$2:$A$1001,">="&$A12,Running_Costs!$A$2:$A$1001,"<"&DATE(YEAR($A12),MONTH($A12)+1,1)) -> 50433 | H12: =SUMIFS(Fixed_Costs!$D$2:$D$501,Fixed_Costs!$A$2:$A$501,">="&$A12,Fixed_Costs!$A$2:$A$501,"<"&DATE(YEAR($A12),MONTH($A12)+1,1)) -> 8000 | I12: =SUMIFS(Owner_Capital!$C$2:$C$501,Owner_Capital!$B$2:$B$501,"Owner Drawing",Owner_Capital!$A$2:$A$501,">="&$A12,Owner_Capital!$A$2:$A$501,"<"&DATE(YEAR($A12),MONTH($A12)+1,1)) -> 0 | J12: =SUM(F12:I12) -> 119463 | K12: =E12-J12 -> 120727 | L12: =L11+K12 -> 185727 | M12: =F12+H12 -> 69030 | N12: =F12-Profit!E12 -> -123730 | O12: =IF(Profit!D12=0,0,M12/Profit!D12) -> 0.26235178 | P12: =Profit!H12-I12 -> 27927
A13: =DATE(Settings!$B$9,9,1) -> 46266 | B13: =SUMIFS(Sales_Memo!$H$2:$H$1001,Sales_Memo!$B$2:$B$1001,">="&$A13,Sales_Memo!$B$2:$B$1001,"<"&DATE(YEAR($A13),MONTH($A13)+1,1)) -> 249280 | C13: =SUMIFS(Due_Payments!$C$2:$C$1001,Due_Payments!$A$2:$A$1001,">="&$A13,Due_Payments!$A$2:$A$1001,"<"&DATE(YEAR($A13),MONTH($A13)+1,1)) -> 15820 | D13: =SUMIFS(Owner_Capital!$C$2:$C$501,Owner_Capital!$B$2:$B$501,"Capital In",Owner_Capital!$A$2:$A$501,">="&$A13,Owner_Capital!$A$2:$A$501,"<"&DATE(YEAR($A13),MONTH($A13)+1,1)) -> 0 | E13: =SUM(B13:D13) -> 265100 | F13: =SUMIFS(Purchases!$F$2:$F$2001,Purchases!$A$2:$A$2001,">="&$A13,Purchases!$A$2:$A$2001,"<"&DATE(YEAR($A13),MONTH($A13)+1,1)) -> 205580 | G13: =SUMIFS(Running_Costs!$D$2:$D$1001,Running_Costs!$A$2:$A$1001,">="&$A13,Running_Costs!$A$2:$A$1001,"<"&DATE(YEAR($A13),MONTH($A13)+1,1)) -> 51591 | H13: =SUMIFS(Fixed_Costs!$D$2:$D$501,Fixed_Costs!$A$2:$A$501,">="&$A13,Fixed_Costs!$A$2:$A$501,"<"&DATE(YEAR($A13),MONTH($A13)+1,1)) -> 0 | I13: =SUMIFS(Owner_Capital!$C$2:$C$501,Owner_Capital!$B$2:$B$501,"Owner Drawing",Owner_Capital!$A$2:$A$501,">="&$A13,Owner_Capital!$A$2:$A$501,"<"&DATE(YEAR($A13),MONTH($A13)+1,1)) -> 10000 | J13: =SUM(F13:I13) -> 267171 | K13: =E13-J13 -> -2071 | L13: =L12+K13 -> 183656 | M13: =F13+H13 -> 205580 | N13: =F13-Profit!E13 -> 8020 | O13: =IF(Profit!D13=0,0,M13/Profit!D13) -> 0.72359297 | P13: =Profit!H13-I13 -> 24959
A14: =DATE(Settings!$B$9,10,1) -> 46296 | B14: =SUMIFS(Sales_Memo!$H$2:$H$1001,Sales_Memo!$B$2:$B$1001,">="&$A14,Sales_Memo!$B$2:$B$1001,"<"&DATE(YEAR($A14),MONTH($A14)+1,1)) -> 199550 | C14: =SUMIFS(Due_Payments!$C$2:$C$1001,Due_Payments!$A$2:$A$1001,">="&$A14,Due_Payments!$A$2:$A$1001,"<"&DATE(YEAR($A14),MONTH($A14)+1,1)) -> 8890 | D14: =SUMIFS(Owner_Capital!$C$2:$C$501,Owner_Capital!$B$2:$B$501,"Capital In",Owner_Capital!$A$2:$A$501,">="&$A14,Owner_Capital!$A$2:$A$501,"<"&DATE(YEAR($A14),MONTH($A14)+1,1)) -> 0 | E14: =SUM(B14:D14) -> 208440 | F14: =SUMIFS(Purchases!$F$2:$F$2001,Purchases!$A$2:$A$2001,">="&$A14,Purchases!$A$2:$A$2001,"<"&DATE(YEAR($A14),MONTH($A14)+1,1)) -> 160260 | G14: =SUMIFS(Running_Costs!$D$2:$D$1001,Running_Costs!$A$2:$A$1001,">="&$A14,Running_Costs!$A$2:$A$1001,"<"&DATE(YEAR($A14),MONTH($A14)+1,1)) -> 50180 | H14: =SUMIFS(Fixed_Costs!$D$2:$D$501,Fixed_Costs!$A$2:$A$501,">="&$A14,Fixed_Costs!$A$2:$A$501,"<"&DATE(YEAR($A14),MONTH($A14)+1,1)) -> 0 | I14: =SUMIFS(Owner_Capital!$C$2:$C$501,Owner_Capital!$B$2:$B$501,"Owner Drawing",Owner_Capital!$A$2:$A$501,">="&$A14,Owner_Capital!$A$2:$A$501,"<"&DATE(YEAR($A14),MONTH($A14)+1,1)) -> 8000 | J14: =SUM(F14:I14) -> 218440 | K14: =E14-J14 -> -10000 | L14: =L13+K14 -> 173656 | M14: =F14+H14 -> 160260 | N14: =F14-Profit!E14 -> 4640 | O14: =IF(Profit!D14=0,0,M14/Profit!D14) -> 0.72069074 | P14: =Profit!H14-I14 -> 8570
A15: =DATE(Settings!$B$9,11,1) -> 46327 | B15: =SUMIFS(Sales_Memo!$H$2:$H$1001,Sales_Memo!$B$2:$B$1001,">="&$A15,Sales_Memo!$B$2:$B$1001,"<"&DATE(YEAR($A15),MONTH($A15)+1,1)) -> 0 | C15: =SUMIFS(Due_Payments!$C$2:$C$1001,Due_Payments!$A$2:$A$1001,">="&$A15,Due_Payments!$A$2:$A$1001,"<"&DATE(YEAR($A15),MONTH($A15)+1,1)) -> 0 | D15: =SUMIFS(Owner_Capital!$C$2:$C$501,Owner_Capital!$B$2:$B$501,"Capital In",Owner_Capital!$A$2:$A$501,">="&$A15,Owner_Capital!$A$2:$A$501,"<"&DATE(YEAR($A15),MONTH($A15)+1,1)) -> 0 | E15: =SUM(B15:D15) -> 0 | F15: =SUMIFS(Purchases!$F$2:$F$2001,Purchases!$A$2:$A$2001,">="&$A15,Purchases!$A$2:$A$2001,"<"&DATE(YEAR($A15),MONTH($A15)+1,1)) -> 0 | G15: =SUMIFS(Running_Costs!$D$2:$D$1001,Running_Costs!$A$2:$A$1001,">="&$A15,Running_Costs!$A$2:$A$1001,"<"&DATE(YEAR($A15),MONTH($A15)+1,1)) -> 0 | H15: =SUMIFS(Fixed_Costs!$D$2:$D$501,Fixed_Costs!$A$2:$A$501,">="&$A15,Fixed_Costs!$A$2:$A$501,"<"&DATE(YEAR($A15),MONTH($A15)+1,1)) -> 0 | I15: =SUMIFS(Owner_Capital!$C$2:$C$501,Owner_Capital!$B$2:$B$501,"Owner Drawing",Owner_Capital!$A$2:$A$501,">="&$A15,Owner_Capital!$A$2:$A$501,"<"&DATE(YEAR($A15),MONTH($A15)+1,1)) -> 0 | J15: =SUM(F15:I15) -> 0 | K15: =E15-J15 -> 0 | L15: =L14+K15 -> 173656 | M15: =F15+H15 -> 0 | N15: =F15-Profit!E15 -> 0 | O15: =IF(Profit!D15=0,0,M15/Profit!D15) -> 0 | P15: =Profit!H15-I15 -> 0
A16: =DATE(Settings!$B$9,12,1) -> 46357 | B16: =SUMIFS(Sales_Memo!$H$2:$H$1001,Sales_Memo!$B$2:$B$1001,">="&$A16,Sales_Memo!$B$2:$B$1001,"<"&DATE(YEAR($A16),MONTH($A16)+1,1)) -> 0 | C16: =SUMIFS(Due_Payments!$C$2:$C$1001,Due_Payments!$A$2:$A$1001,">="&$A16,Due_Payments!$A$2:$A$1001,"<"&DATE(YEAR($A16),MONTH($A16)+1,1)) -> 0 | D16: =SUMIFS(Owner_Capital!$C$2:$C$501,Owner_Capital!$B$2:$B$501,"Capital In",Owner_Capital!$A$2:$A$501,">="&$A16,Owner_Capital!$A$2:$A$501,"<"&DATE(YEAR($A16),MONTH($A16)+1,1)) -> 0 | E16: =SUM(B16:D16) -> 0 | F16: =SUMIFS(Purchases!$F$2:$F$2001,Purchases!$A$2:$A$2001,">="&$A16,Purchases!$A$2:$A$2001,"<"&DATE(YEAR($A16),MONTH($A16)+1,1)) -> 0 | G16: =SUMIFS(Running_Costs!$D$2:$D$1001,Running_Costs!$A$2:$A$1001,">="&$A16,Running_Costs!$A$2:$A$1001,"<"&DATE(YEAR($A16),MONTH($A16)+1,1)) -> 0 | H16: =SUMIFS(Fixed_Costs!$D$2:$D$501,Fixed_Costs!$A$2:$A$501,">="&$A16,Fixed_Costs!$A$2:$A$501,"<"&DATE(YEAR($A16),MONTH($A16)+1,1)) -> 0 | I16: =SUMIFS(Owner_Capital!$C$2:$C$501,Owner_Capital!$B$2:$B$501,"Owner Drawing",Owner_Capital!$A$2:$A$501,">="&$A16,Owner_Capital!$A$2:$A$501,"<"&DATE(YEAR($A16),MONTH($A16)+1,1)) -> 0 | J16: =SUM(F16:I16) -> 0 | K16: =E16-J16 -> 0 | L16: =L15+K16 -> 173656 | M16: =F16+H16 -> 0 | N16: =F16-Profit!E16 -> 0 | O16: =IF(Profit!D16=0,0,M16/Profit!D16) -> 0 | P16: =Profit!H16-I16 -> 0
A17: TOTAL | B17: =SUM(B5:B16) -> 678020 | C17: =SUM(C5:C16) -> 35710 | D17: =SUM(D5:D16) -> 300000 | E17: =SUM(E5:E16) -> 1013730 | F17: =SUM(F5:F16) -> 426870 | G17: =SUM(G5:G16) -> 152204 | H17: =SUM(H5:H16) -> 243000 | I17: =SUM(I5:I16) -> 18000 | ... K17: =SUM(K5:K16) -> 173656 | L17: =L16 -> 173656 | M17: =SUM(M5:M16) -> 669870 | N17: =SUM(N5:N16) -> -111070 | O17: =IF(Profit!D17=0,0,M17/Profit!D17) -> 0.8704132 | P17: =SUM(P5:P16) -> 61456

Sheet Dashboard
A1: DASHBOARD | C1: =Settings!B3&" | Year "&Settings!B9 -> My Bike Parts Shop | Year 2026
A3: Net Sales (year) | B3: =Profit!D17 -> 769600
A4: Gross Profit | B4: =Profit!F17 -> 231660
A5: Operating Profit | B5: =Profit!H17 -> 79456
A6: Total Due from Customers | B6: =SUM(Sales_Memo!$J$2:$J$1001) -> 55870
A7: Stock Value (at buy price) | B7: =SUM(Stock!I2:I501) -> 226290
A8: Items Low / Out of Stock | B8: =COUNTIF(Stock!K2:K501,"LOW")+COUNTIF(Stock!K2:K501,"OUT") -> 3
A9: Reinvested (gross, year) | B9: =Reinvestment!M17 -> 669870
A10: Cash in Hand (end of year) | B10: =Reinvestment!L16 -> 173656
A12: TOP 10 SELLING ITEMS
A13: Item | B13: Code | C13: Qty Sold
A14: =IFERROR(IF(LARGE(Stock!$L$2:$L$501,1)<1,"",INDEX(Stock!$B$2:$B$501,MATCH(LARGE(Stock!$L$2:$L$501,1),Stock!$L$2:$L$501,0))),"") -> Clutch Cable | B14: =IF(A14="","",INDEX(Stock!$A$2:$A$501,MATCH(LARGE(Stock!$L$2:$L$501,1),Stock!$L$2:$L$501,0))) -> BP002 | C14: =IF(A14="","",INDEX(Stock!$F$2:$F$501,MATCH(LARGE(Stock!$L$2:$L$501,1),Stock!$L$2:$L$501,0))) -> 347
A15: =IFERROR(IF(LARGE(Stock!$L$2:$L$501,2)<1,"",INDEX(Stock!$B$2:$B$501,MATCH(LARGE(Stock!$L$2:$L$501,2),Stock!$L$2:$L$501,0))),"") -> Headlight Bulb H4 | B15: =IF(A15="","",INDEX(Stock!$A$2:$A$501,MATCH(LARGE(Stock!$L$2:$L$501,2),Stock!$L$2:$L$501,0))) -> BP008 | C15: =IF(A15="","",INDEX(Stock!$F$2:$F$501,MATCH(LARGE(Stock!$L$2:$L$501,2),Stock!$L$2:$L$501,0))) -> 264
A16: =IFERROR(IF(LARGE(Stock!$L$2:$L$501,3)<1,"",INDEX(Stock!$B$2:$B$501,MATCH(LARGE(Stock!$L$2:$L$501,3),Stock!$L$2:$L$501,0))),"") -> Spark Plug CPR8EA-9 | B16: =IF(A16="","",INDEX(Stock!$A$2:$A$501,MATCH(LARGE(Stock!$L$2:$L$501,3),Stock!$L$2:$L$501,0))) -> BP003 | C16: =IF(A16="","",INDEX(Stock!$F$2:$F$501,MATCH(LARGE(Stock!$L$2:$L$501,3),Stock!$L$2:$L$501,0))) -> 222
A17: =IFERROR(IF(LARGE(Stock!$L$2:$L$501,4)<1,"",INDEX(Stock!$B$2:$B$501,MATCH(LARGE(Stock!$L$2:$L$501,4),Stock!$L$2:$L$501,0))),"") -> Chain Lube Spray | B17: =IF(A17="","",INDEX(Stock!$A$2:$A$501,MATCH(LARGE(Stock!$L$2:$L$501,4),Stock!$L$2:$L$501,0))) -> BP014 | C17: =IF(A17="","",INDEX(Stock!$F$2:$F$501,MATCH(LARGE(Stock!$L$2:$L$501,4),Stock!$L$2:$L$501,0))) -> 217
A18: =IFERROR(IF(LARGE(Stock!$L$2:$L$501,5)<1,"",INDEX(Stock!$B$2:$B$501,MATCH(LARGE(Stock!$L$2:$L$501,5),Stock!$L$2:$L$501,0))),"") -> Handle Grip Set | B18: =IF(A18="","",INDEX(Stock!$A$2:$A$501,MATCH(LARGE(Stock!$L$2:$L$501,5),Stock!$L$2:$L$501,0))) -> BP015 | C18: =IF(A18="","",INDEX(Stock!$F$2:$F$501,MATCH(LARGE(Stock!$L$2:$L$501,5),Stock!$L$2:$L$501,0))) -> 211
A19: =IFERROR(IF(LARGE(Stock!$L$2:$L$501,6)<1,"",INDEX(Stock!$B$2:$B$501,MATCH(LARGE(Stock!$L$2:$L$501,6),Stock!$L$2:$L$501,0))),"") -> Air Filter 150cc | B19: =IF(A19="","",INDEX(Stock!$A$2:$A$501,MATCH(LARGE(Stock!$L$2:$L$501,6),Stock!$L$2:$L$501,0))) -> BP004 | C19: =IF(A19="","",INDEX(Stock!$F$2:$F$501,MATCH(LARGE(Stock!$L$2:$L$501,6),Stock!$L$2:$L$501,0))) -> 174
A20: =IFERROR(IF(LARGE(Stock!$L$2:$L$501,7)<1,"",INDEX(Stock!$B$2:$B$501,MATCH(LARGE(Stock!$L$2:$L$501,7),Stock!$L$2:$L$501,0))),"") -> Brake Pad Set - Front | B20: =IF(A20="","",INDEX(Stock!$A$2:$A$501,MATCH(LARGE(Stock!$L$2:$L$501,7),Stock!$L$2:$L$501,0))) -> BP001 | C20: =IF(A20="","",INDEX(Stock!$F$2:$F$501,MATCH(LARGE(Stock!$L$2:$L$501,7),Stock!$L$2:$L$501,0))) -> 112
A21: =IFERROR(IF(LARGE(Stock!$L$2:$L$501,8)<1,"",INDEX(Stock!$B$2:$B$501,MATCH(LARGE(Stock!$L$2:$L$501,8),Stock!$L$2:$L$501,0))),"") -> Engine Oil 10W-30 (1L) | B21: =IF(A21="","",INDEX(Stock!$A$2:$A$501,MATCH(LARGE(Stock!$L$2:$L$501,8),Stock!$L$2:$L$501,0))) -> BP006 | C21: =IF(A21="","",INDEX(Stock!$F$2:$F$501,MATCH(LARGE(Stock!$L$2:$L$501,8),Stock!$L$2:$L$501,0))) -> 101
A22: =IFERROR(IF(LARGE(Stock!$L$2:$L$501,9)<1,"",INDEX(Stock!$B$2:$B$501,MATCH(LARGE(Stock!$L$2:$L$501,9),Stock!$L$2:$L$501,0))),"") -> Engine Oil 20W-50 (1L) | B22: =IF(A22="","",INDEX(Stock!$A$2:$A$501,MATCH(LARGE(Stock!$L$2:$L$501,9),Stock!$L$2:$L$501,0))) -> BP007 | C22: =IF(A22="","",INDEX(Stock!$F$2:$F$501,MATCH(LARGE(Stock!$L$2:$L$501,9),Stock!$L$2:$L$501,0))) -> 97
A23: =IFERROR(IF(LARGE(Stock!$L$2:$L$501,10)<1,"",INDEX(Stock!$B$2:$B$501,MATCH(LARGE(Stock!$L$2:$L$501,10),Stock!$L$2:$L$501,0))),"") -> Side Mirror (Pair) | B23: =IF(A23="","",INDEX(Stock!$A$2:$A$501,MATCH(LARGE(Stock!$L$2:$L$501,10),Stock!$L$2:$L$501,0))) -> BP012 | C23: =IF(A23="","",INDEX(Stock!$F$2:$F$501,MATCH(LARGE(Stock!$L$2:$L$501,10),Stock!$L$2:$L$501,0))) -> 80
A25: LOW / OUT OF STOCK
A26: Item | B26: Current | C26: Min Alert | D26: Status
A27: =IFERROR(INDEX(Stock!$B$2:$B$501,MATCH(1,Stock!$M$2:$M$501,0)),"") -> Clutch Cable | B27: =IFERROR(INDEX(Stock!$G$2:$G$501,MATCH(1,Stock!$M$2:$M$501,0)),"") -> 7 | C27: =IFERROR(INDEX(Stock!$J$2:$J$501,MATCH(1,Stock!$M$2:$M$501,0)),"") -> 10 | D27: =IFERROR(INDEX(Stock!$K$2:$K$501,MATCH(1,Stock!$M$2:$M$501,0)),"") -> LOW
A28: =IFERROR(INDEX(Stock!$B$2:$B$501,MATCH(2,Stock!$M$2:$M$501,0)),"") -> Battery 12V 5Ah | B28: =IFERROR(INDEX(Stock!$G$2:$G$501,MATCH(2,Stock!$M$2:$M$501,0)),"") -> 0 | C28: =IFERROR(INDEX(Stock!$J$2:$J$501,MATCH(2,Stock!$M$2:$M$501,0)),"") -> 3 | D28: =IFERROR(INDEX(Stock!$K$2:$K$501,MATCH(2,Stock!$M$2:$M$501,0)),"") -> OUT
A29: =IFERROR(INDEX(Stock!$B$2:$B$501,MATCH(3,Stock!$M$2:$M$501,0)),"") -> Helmet Full Face | B29: =IFERROR(INDEX(Stock!$G$2:$G$501,MATCH(3,Stock!$M$2:$M$501,0)),"") -> 0 | C29: =IFERROR(INDEX(Stock!$J$2:$J$501,MATCH(3,Stock!$M$2:$M$501,0)),"") -> 5 | D29: =IFERROR(INDEX(Stock!$K$2:$K$501,MATCH(3,Stock!$M$2:$M$501,0)),"") -> OUT
A30: =IFERROR(INDEX(Stock!$B$2:$B$501,MATCH(4,Stock!$M$2:$M$501,0)),"") | B30: =IFERROR(INDEX(Stock!$G$2:$G$501,MATCH(4,Stock!$M$2:$M$501,0)),"") | C30: =IFERROR(INDEX(Stock!$J$2:$J$501,MATCH(4,Stock!$M$2:$M$501,0)),"") | D30: =IFERROR(INDEX(Stock!$K$2:$K$501,MATCH(4,Stock!$M$2:$M$501,0)),"")
A31: =IFERROR(INDEX(Stock!$B$2:$B$501,MATCH(5,Stock!$M$2:$M$501,0)),"") | B31: =IFERROR(INDEX(Stock!$G$2:$G$501,MATCH(5,Stock!$M$2:$M$501,0)),"") | C31: =IFERROR(INDEX(Stock!$J$2:$J$501,MATCH(5,Stock!$M$2:$M$501,0)),"") | D31: =IFERROR(INDEX(Stock!$K$2:$K$501,MATCH(5,Stock!$M$2:$M$501,0)),"")
A32: =IFERROR(INDEX(Stock!$B$2:$B$501,MATCH(6,Stock!$M$2:$M$501,0)),"") | B32: =IFERROR(INDEX(Stock!$G$2:$G$501,MATCH(6,Stock!$M$2:$M$501,0)),"") | C32: =IFERROR(INDEX(Stock!$J$2:$J$501,MATCH(6,Stock!$M$2:$M$501,0)),"") | D32: =IFERROR(INDEX(Stock!$K$2:$K$501,MATCH(6,Stock!$M$2:$M$501,0)),"")
A33: =IFERROR(INDEX(Stock!$B$2:$B$501,MATCH(7,Stock!$M$2:$M$501,0)),"") | B33: =IFERROR(INDEX(Stock!$G$2:$G$501,MATCH(7,Stock!$M$2:$M$501,0)),"") | C33: =IFERROR(INDEX(Stock!$J$2:$J$501,MATCH(7,Stock!$M$2:$M$501,0)),"") | D33: =IFERROR(INDEX(Stock!$K$2:$K$501,MATCH(7,Stock!$M$2:$M$501,0)),"")
A34: =IFERROR(INDEX(Stock!$B$2:$B$501,MATCH(8,Stock!$M$2:$M$501,0)),"") | B34: =IFERROR(INDEX(Stock!$G$2:$G$501,MATCH(8,Stock!$M$2:$M$501,0)),"") | C34: =IFERROR(INDEX(Stock!$J$2:$J$501,MATCH(8,Stock!$M$2:$M$501,0)),"") | D34: =IFERROR(INDEX(Stock!$K$2:$K$501,MATCH(8,Stock!$M$2:$M$501,0)),"")
A35: =IFERROR(INDEX(Stock!$B$2:$B$501,MATCH(9,Stock!$M$2:$M$501,0)),"") | B35: =IFERROR(INDEX(Stock!$G$2:$G$501,MATCH(9,Stock!$M$2:$M$501,0)),"") | C35: =IFERROR(INDEX(Stock!$J$2:$J$501,MATCH(9,Stock!$M$2:$M$501,0)),"") | D35: =IFERROR(INDEX(Stock!$K$2:$K$501,MATCH(9,Stock!$M$2:$M$501,0)),"")
A36: =IFERROR(INDEX(Stock!$B$2:$B$501,MATCH(10,Stock!$M$2:$M$501,0)),"") | B36: =IFERROR(INDEX(Stock!$G$2:$G$501,MATCH(10,Stock!$M$2:$M$501,0)),"") | C36: =IFERROR(INDEX(Stock!$J$2:$J$501,MATCH(10,Stock!$M$2:$M$501,0)),"") | D36: =IFERROR(INDEX(Stock!$K$2:$K$501,MATCH(10,Stock!$M$2:$M$501,0)),"")
A38: RUNNING COSTS BY CATEGORY (year)
A39: Category | B39: Amount
A40: =Settings!G3 -> Electricity | B40: =IF(A40="",0,SUMIFS(Running_Costs!$D$2:$D$1001,Running_Costs!$B$2:$B$1001,A40,Running_Costs!$A$2:$A$1001,">="&DATE(Settings!$B$9,1,1),Running_Costs!$A$2:$A$1001,"<"&DATE(Settings!$B$9+1,1,1))) -> 9343
A41: =Settings!G4 -> Internet | B41: =IF(A41="",0,SUMIFS(Running_Costs!$D$2:$D$1001,Running_Costs!$B$2:$B$1001,A41,Running_Costs!$A$2:$A$1001,">="&DATE(Settings!$B$9,1,1),Running_Costs!$A$2:$A$1001,"<"&DATE(Settings!$B$9+1,1,1))) -> 3000
A42: =Settings!G5 -> Salary | B42: =IF(A42="",0,SUMIFS(Running_Costs!$D$2:$D$1001,Running_Costs!$B$2:$B$1001,A42,Running_Costs!$A$2:$A$1001,">="&DATE(Settings!$B$9,1,1),Running_Costs!$A$2:$A$1001,"<"&DATE(Settings!$B$9+1,1,1))) -> 72000
A43: =Settings!G6 -> Rent | B43: =IF(A43="",0,SUMIFS(Running_Costs!$D$2:$D$1001,Running_Costs!$B$2:$B$1001,A43,Running_Costs!$A$2:$A$1001,">="&DATE(Settings!$B$9,1,1),Running_Costs!$A$2:$A$1001,"<"&DATE(Settings!$B$9+1,1,1))) -> 60000
A44: =Settings!G7 -> Transport | B44: =IF(A44="",0,SUMIFS(Running_Costs!$D$2:$D$1001,Running_Costs!$B$2:$B$1001,A44,Running_Costs!$A$2:$A$1001,">="&DATE(Settings!$B$9,1,1),Running_Costs!$A$2:$A$1001,"<"&DATE(Settings!$B$9+1,1,1))) -> 4826
A45: =Settings!G8 -> Other | B45: =IF(A45="",0,SUMIFS(Running_Costs!$D$2:$D$1001,Running_Costs!$B$2:$B$1001,A45,Running_Costs!$A$2:$A$1001,">="&DATE(Settings!$B$9,1,1),Running_Costs!$A$2:$A$1001,"<"&DATE(Settings!$B$9+1,1,1))) -> 3035
A47: FIXED COSTS BY CATEGORY (year)
A48: Category | B48: Amount
A49: =Settings!H3 -> Decoration | B49: =IF(A49="",0,SUMIFS(Fixed_Costs!$D$2:$D$501,Fixed_Costs!$B$2:$B$501,A49,Fixed_Costs!$A$2:$A$501,">="&DATE(Settings!$B$9,1,1),Fixed_Costs!$A$2:$A$501,"<"&DATE(Settings!$B$9+1,1,1))) -> 145000
A50: =Settings!H4 -> Furniture | B50: =IF(A50="",0,SUMIFS(Fixed_Costs!$D$2:$D$501,Fixed_Costs!$B$2:$B$501,A50,Fixed_Costs!$A$2:$A$501,">="&DATE(Settings!$B$9,1,1),Fixed_Costs!$A$2:$A$501,"<"&DATE(Settings!$B$9+1,1,1))) -> 60000
A51: =Settings!H5 -> Equipment | B51: =IF(A51="",0,SUMIFS(Fixed_Costs!$D$2:$D$501,Fixed_Costs!$B$2:$B$501,A51,Fixed_Costs!$A$2:$A$501,">="&DATE(Settings!$B$9,1,1),Fixed_Costs!$A$2:$A$501,"<"&DATE(Settings!$B$9+1,1,1))) -> 30000
A52: =Settings!H6 -> Repair | B52: =IF(A52="",0,SUMIFS(Fixed_Costs!$D$2:$D$501,Fixed_Costs!$B$2:$B$501,A52,Fixed_Costs!$A$2:$A$501,">="&DATE(Settings!$B$9,1,1),Fixed_Costs!$A$2:$A$501,"<"&DATE(Settings!$B$9+1,1,1))) -> 0
A53: =Settings!H7 -> Materials | B53: =IF(A53="",0,SUMIFS(Fixed_Costs!$D$2:$D$501,Fixed_Costs!$B$2:$B$501,A53,Fixed_Costs!$A$2:$A$501,">="&DATE(Settings!$B$9,1,1),Fixed_Costs!$A$2:$A$501,"<"&DATE(Settings!$B$9+1,1,1))) -> 8000
A54: =Settings!H8 -> Other | B54: =IF(A54="",0,SUMIFS(Fixed_Costs!$D$2:$D$501,Fixed_Costs!$B$2:$B$501,A54,Fixed_Costs!$A$2:$A$501,">="&DATE(Settings!$B$9,1,1),Fixed_Costs!$A$2:$A$501,"<"&DATE(Settings!$B$9+1,1,1))) -> 0
